[
  {
    "客戶編號": "Z001",
    "使用集團設定": null,
    "集團包裝要求(代入)": null,
    "訂單包裝要求(顯示)": null,
    "客戶簡稱": "ZIMEX",
    "報告email": null,
    "客戶包裝要求": null,
    "客戶集團代號": null,
    "負責業務": null,
    "分部位置": null,
    "幣別": null,
    "客戶全名": "ZIMEX INTERNATIONAL B.V.",
    "匯率": null,
    "客戶地址": "NIELS BOHRSTAAT 24-1 6716 AM EDE\r\nPOSTUBS 26 6710 BA EDE\r\nNETHERLAND",
    "付款日期": null,
    "客戶電話": "002-31-85690075",
    "發票地址": null,
    "客戶傳真": "002-31-8575069",
    "invoice Email": "jeroen@zimex.nl",
    "供應商電話": null,
    "供應商傳真": null,
    "客人負責人": null,
    "客人聯絡人": "HEROEN M. NOORMAN",
    "供應商聯絡人": null,
    "客人採購": null,
    "客人業務": null,
    "負責船務": null,
    "標籤": null,
    "棧板格式": null,
    "出歐洲 CBAMnote": null,
    "SC shipping  mark": null,
    "紙箱格式": null,
    "Ship to add.": null,
    "整箱重量 max": null,
    "Payment term": null,
    "交貨條件": null,
    "Packing info": null,
    "付款條件": null,
    "Q'ty Allowance%": null,
    "包裝資訊": null,
    "Reports": null,
    "允收量%": null,
    "索取報告": null,
    "舊系統備註": null
  },
  {
    "客戶編號": "Y001",
    "使用集團設定": null,
    "集團包裝要求(代入)": null,
    "訂單包裝要求(顯示)": null,
    "客戶簡稱": "YAMASHIN",
    "報告email": null,
    "客戶包裝要求": null,
    "客戶集團代號": null,
    "負責業務": null,
    "分部位置": null,
    "幣別": null,
    "客戶全名": "YAMASHIN INDUSTRY CO. INC.",
    "匯率": null,
    "客戶地址": "CENTRAL P.O. BOX 1483\nOSAKA 530-91\nJAPAN",
    "付款日期": null,
    "客戶電話": "81-6-768-0820",
    "發票地址": null,
    "客戶傳真": "81-6-764-5538",
    "invoice Email": null,
    "供應商電話": null,
    "供應商傳真": null,
    "客人負責人": null,
    "客人聯絡人": "TOSHI",
    "供應商聯絡人": null,
    "客人採購": null,
    "客人業務": null,
    "負責船務": null,
    "標籤": null,
    "棧板格式": null,
    "出歐洲 CBAMnote": null,
    "SC shipping  mark": null,
    "紙箱格式": null,
    "Ship to add.": null,
    "整箱重量 max": null,
    "Payment term": null,
    "交貨條件": null,
    "Packing info": null,
    "付款條件": null,
    "Q'ty Allowance%": null,
    "包裝資訊": null,
    "Reports": null,
    "允收量%": null,
    "索取報告": null,
    "舊系統備註": null
  },
  {
    "客戶編號": "XX05",
    "使用集團設定": null,
    "集團包裝要求(代入)": null,
    "訂單包裝要求(顯示)": null,
    "客戶簡稱": "川翼",
    "報告email": null,
    "客戶包裝要求": null,
    "客戶集團代號": null,
    "負責業務": null,
    "分部位置": null,
    "幣別": null,
    "客戶全名": "川翼企業股份有限公司",
    "匯率": null,
    "客戶地址": "新北市新莊區化成路63巷18-1號\n\n",
    "付款日期": null,
    "客戶電話": "886-2-22771061\/1071\/1081",
    "發票地址": null,
    "客戶傳真": "886-2-2277-0800",
    "invoice Email": "river.eagle@msa.hinet.net",
    "供應商電話": null,
    "供應商傳真": null,
    "客人負責人": "陳子庭",
    "客人聯絡人": null,
    "供應商聯絡人": null,
    "客人採購": null,
    "客人業務": null,
    "負責船務": null,
    "標籤": null,
    "棧板格式": null,
    "出歐洲 CBAMnote": null,
    "SC shipping  mark": null,
    "紙箱格式": null,
    "Ship to add.": null,
    "整箱重量 max": null,
    "Payment term": null,
    "交貨條件": null,
    "Packing info": null,
    "付款條件": null,
    "Q'ty Allowance%": null,
    "包裝資訊": null,
    "Reports": null,
    "允收量%": null,
    "索取報告": null,
    "舊系統備註": null
  },
  {
    "客戶編號": "XX04",
    "使用集團設定": null,
    "集團包裝要求(代入)": null,
    "訂單包裝要求(顯示)": null,
    "客戶簡稱": "登琳",
    "報告email": null,
    "客戶包裝要求": null,
    "客戶集團代號": null,
    "負責業務": null,
    "分部位置": null,
    "幣別": null,
    "客戶全名": "登琳實業有限公司",
    "匯率": null,
    "客戶地址": "台北市長安東路一段16號8F-2\n\n",
    "付款日期": null,
    "客戶電話": "(02) 2523-3947",
    "發票地址": null,
    "客戶傳真": "(02) 2523-0870",
    "invoice Email": null,
    "供應商電話": null,
    "供應商傳真": null,
    "客人負責人": null,
    "客人聯絡人": "郭先生",
    "供應商聯絡人": null,
    "客人採購": null,
    "客人業務": null,
    "負責船務": null,
    "標籤": null,
    "棧板格式": null,
    "出歐洲 CBAMnote": null,
    "SC shipping  mark": null,
    "紙箱格式": null,
    "Ship to add.": null,
    "整箱重量 max": null,
    "Payment term": null,
    "交貨條件": null,
    "Packing info": null,
    "付款條件": null,
    "Q'ty Allowance%": null,
    "包裝資訊": null,
    "Reports": null,
    "允收量%": null,
    "索取報告": null,
    "舊系統備註": "出貨文件  - 請參閱出貨文件檔"
  },
  {
    "客戶編號": "XX03",
    "使用集團設定": null,
    "集團包裝要求(代入)": null,
    "訂單包裝要求(顯示)": null,
    "客戶簡稱": "立進",
    "報告email": null,
    "客戶包裝要求": null,
    "客戶集團代號": null,
    "負責業務": null,
    "分部位置": null,
    "幣別": null,
    "客戶全名": "立進興業有限公司",
    "匯率": null,
    "客戶地址": "桃園縣楊梅鎮楊湖路1段682號\n\n",
    "付款日期": null,
    "客戶電話": "(03)4850255",
    "發票地址": null,
    "客戶傳真": "(03)4850070",
    "invoice Email": null,
    "供應商電話": null,
    "供應商傳真": null,
    "客人負責人": null,
    "客人聯絡人": null,
    "供應商聯絡人": null,
    "客人採購": null,
    "客人業務": null,
    "負責船務": null,
    "標籤": null,
    "棧板格式": null,
    "出歐洲 CBAMnote": null,
    "SC shipping  mark": null,
    "紙箱格式": null,
    "Ship to add.": null,
    "整箱重量 max": null,
    "Payment term": null,
    "交貨條件": null,
    "Packing info": null,
    "付款條件": null,
    "Q'ty Allowance%": null,
    "包裝資訊": null,
    "Reports": null,
    "允收量%": null,
    "索取報告": null,
    "舊系統備註": null
  },
  {
    "客戶編號": "XX02",
    "使用集團設定": null,
    "集團包裝要求(代入)": null,
    "訂單包裝要求(顯示)": null,
    "客戶簡稱": "煒承",
    "報告email": null,
    "客戶包裝要求": null,
    "客戶集團代號": null,
    "負責業務": null,
    "分部位置": null,
    "幣別": null,
    "客戶全名": "煒承精密工業股份有限公司",
    "匯率": null,
    "客戶地址": "新莊市化成路63巷19號\n\n",
    "付款日期": null,
    "客戶電話": "02-29974850",
    "發票地址": null,
    "客戶傳真": null,
    "invoice Email": null,
    "供應商電話": null,
    "供應商傳真": null,
    "客人負責人": null,
    "客人聯絡人": null,
    "供應商聯絡人": null,
    "客人採購": null,
    "客人業務": null,
    "負責船務": null,
    "標籤": null,
    "棧板格式": null,
    "出歐洲 CBAMnote": null,
    "SC shipping  mark": null,
    "紙箱格式": null,
    "Ship to add.": null,
    "整箱重量 max": null,
    "Payment term": null,
    "交貨條件": null,
    "Packing info": null,
    "付款條件": null,
    "Q'ty Allowance%": null,
    "包裝資訊": null,
    "Reports": null,
    "允收量%": null,
    "索取報告": null,
    "舊系統備註": null
  },
  {
    "客戶編號": "XX01",
    "使用集團設定": null,
    "集團包裝要求(代入)": null,
    "訂單包裝要求(顯示)": null,
    "客戶簡稱": "宜峰",
    "報告email": null,
    "客戶包裝要求": null,
    "客戶集團代號": null,
    "負責業務": null,
    "分部位置": null,
    "幣別": null,
    "客戶全名": "宜峰",
    "匯率": null,
    "客戶地址": "\n\n",
    "付款日期": null,
    "客戶電話": "02-29296026 EX 11",
    "發票地址": null,
    "客戶傳真": "02-2928-6170",
    "invoice Email": "p12117@ms15.hinet.net",
    "供應商電話": null,
    "供應商傳真": null,
    "客人負責人": null,
    "客人聯絡人": null,
    "供應商聯絡人": null,
    "客人採購": null,
    "客人業務": null,
    "負責船務": null,
    "標籤": null,
    "棧板格式": null,
    "出歐洲 CBAMnote": null,
    "SC shipping  mark": null,
    "紙箱格式": null,
    "Ship to add.": null,
    "整箱重量 max": null,
    "Payment term": null,
    "交貨條件": null,
    "Packing info": null,
    "付款條件": null,
    "Q'ty Allowance%": null,
    "包裝資訊": null,
    "Reports": null,
    "允收量%": null,
    "索取報告": null,
    "舊系統備註": "劉S"
  },
  {
    "客戶編號": "W902",
    "使用集團設定": null,
    "集團包裝要求(代入)": null,
    "訂單包裝要求(顯示)": null,
    "客戶簡稱": "萬錡",
    "報告email": null,
    "客戶包裝要求": null,
    "客戶集團代號": null,
    "負責業務": null,
    "分部位置": null,
    "幣別": null,
    "客戶全名": "萬錡股份有限公司",
    "匯率": null,
    "客戶地址": "高雄市橋頭區新興路111號 (825)\n\n",
    "付款日期": null,
    "客戶電話": "07-6116608",
    "發票地址": null,
    "客戶傳真": "07-6114090",
    "invoice Email": null,
    "供應商電話": null,
    "供應商傳真": null,
    "客人負責人": null,
    "客人聯絡人": "梁's",
    "供應商聯絡人": null,
    "客人採購": null,
    "客人業務": null,
    "負責船務": null,
    "標籤": null,
    "棧板格式": null,
    "出歐洲 CBAMnote": null,
    "SC shipping  mark": null,
    "紙箱格式": null,
    "Ship to add.": null,
    "整箱重量 max": null,
    "Payment term": null,
    "交貨條件": null,
    "Packing info": null,
    "付款條件": null,
    "Q'ty Allowance%": null,
    "包裝資訊": null,
    "Reports": null,
    "允收量%": null,
    "索取報告": null,
    "舊系統備註": null
  },
  {
    "客戶編號": "W901",
    "使用集團設定": null,
    "集團包裝要求(代入)": null,
    "訂單包裝要求(顯示)": null,
    "客戶簡稱": "王斯",
    "報告email": null,
    "客戶包裝要求": null,
    "客戶集團代號": null,
    "負責業務": null,
    "分部位置": null,
    "幣別": null,
    "客戶全名": "英商王斯有限公司台灣分公司",
    "匯率": null,
    "客戶地址": "台中市西區大隆路20號7F-4號\n\n",
    "付款日期": null,
    "客戶電話": "04-23281129",
    "發票地址": null,
    "客戶傳真": "04-23281320",
    "invoice Email": null,
    "供應商電話": null,
    "供應商傳真": null,
    "客人負責人": null,
    "客人聯絡人": null,
    "供應商聯絡人": null,
    "客人採購": null,
    "客人業務": null,
    "負責船務": null,
    "標籤": null,
    "棧板格式": null,
    "出歐洲 CBAMnote": null,
    "SC shipping  mark": null,
    "紙箱格式": null,
    "Ship to add.": null,
    "整箱重量 max": null,
    "Payment term": null,
    "交貨條件": null,
    "Packing info": null,
    "付款條件": null,
    "Q'ty Allowance%": null,
    "包裝資訊": null,
    "Reports": null,
    "允收量%": null,
    "索取報告": null,
    "舊系統備註": null
  },
  {
    "客戶編號": "W012",
    "使用集團設定": null,
    "集團包裝要求(代入)": null,
    "訂單包裝要求(顯示)": null,
    "客戶簡稱": "Wurth",
    "報告email": null,
    "客戶包裝要求": null,
    "客戶集團代號": null,
    "負責業務": null,
    "分部位置": null,
    "幣別": null,
    "客戶全名": "WURTH REVCAR FASTENERS, INC.(W012 VA)",
    "匯率": null,
    "客戶地址": "1 Avery Row, Roanoke, VA 24012. USA\n",
    "付款日期": null,
    "客戶電話": "540-561-6565",
    "發票地址": null,
    "客戶傳真": "540-5961-6577",
    "invoice Email": "aholland@revcar.com",
    "供應商電話": null,
    "供應商傳真": null,
    "客人負責人": null,
    "客人聯絡人": "Adam Holland",
    "供應商聯絡人": null,
    "客人採購": null,
    "客人業務": null,
    "負責船務": null,
    "標籤": null,
    "棧板格式": null,
    "出歐洲 CBAMnote": null,
    "SC shipping  mark": null,
    "紙箱格式": null,
    "Ship to add.": null,
    "整箱重量 max": null,
    "Payment term": null,
    "交貨條件": null,
    "Packing info": null,
    "付款條件": null,
    "Q'ty Allowance%": null,
    "包裝資訊": null,
    "Reports": null,
    "允收量%": null,
    "索取報告": null,
    "舊系統備註": null
  },
  {
    "客戶編號": "W011",
    "使用集團設定": null,
    "集團包裝要求(代入)": null,
    "訂單包裝要求(顯示)": null,
    "客戶簡稱": "WURTH CANADA",
    "報告email": null,
    "客戶包裝要求": null,
    "客戶集團代號": null,
    "負責業務": null,
    "分部位置": null,
    "幣別": null,
    "客戶全名": "WURTH INDUSTRY OF CANADA LTD.(W011)",
    "匯率": null,
    "客戶地址": "10 ABBOTT COURT, BUILDING B, \nUNIT 203 BRANTFORD ON N3S 0E7\n",
    "付款日期": null,
    "客戶電話": "(519) 756 9700",
    "發票地址": null,
    "客戶傳真": "(519) 756 9701",
    "invoice Email": null,
    "供應商電話": null,
    "供應商傳真": null,
    "客人負責人": null,
    "客人聯絡人": null,
    "供應商聯絡人": null,
    "客人採購": null,
    "客人業務": null,
    "負責船務": null,
    "標籤": null,
    "棧板格式": null,
    "出歐洲 CBAMnote": null,
    "SC shipping  mark": null,
    "紙箱格式": null,
    "Ship to add.": null,
    "整箱重量 max": null,
    "Payment term": null,
    "交貨條件": null,
    "Packing info": null,
    "付款條件": null,
    "Q'ty Allowance%": null,
    "包裝資訊": null,
    "Reports": null,
    "允收量%": null,
    "索取報告": null,
    "舊系統備註": "請款部門 Tyrrell, Tara <tara.tyrrell@wugona.com>\n"
  },
  {
    "客戶編號": "W010",
    "使用集團設定": null,
    "集團包裝要求(代入)": null,
    "訂單包裝要求(顯示)": null,
    "客戶簡稱": "WMTS",
    "報告email": null,
    "客戶包裝要求": null,
    "客戶集團代號": null,
    "負責業務": null,
    "分部位置": null,
    "幣別": null,
    "客戶全名": "THE BOLT BIN\/WEST MICHIGAN TECHNICAL SUPPLY INC.",
    "匯率": null,
    "客戶地址": "11331 3RD AVE NW\nGRAND RAPIDS,MI 49534",
    "付款日期": null,
    "客戶電話": "616-735-0991",
    "發票地址": null,
    "客戶傳真": "616-735-0995",
    "invoice Email": "sales@wmtsinc.com",
    "供應商電話": null,
    "供應商傳真": null,
    "客人負責人": "TIMOTHY IRWIN",
    "客人聯絡人": null,
    "供應商聯絡人": null,
    "客人採購": null,
    "客人業務": null,
    "負責船務": null,
    "標籤": null,
    "棧板格式": null,
    "出歐洲 CBAMnote": null,
    "SC shipping  mark": null,
    "紙箱格式": null,
    "Ship to add.": null,
    "整箱重量 max": null,
    "Payment term": null,
    "交貨條件": null,
    "Packing info": null,
    "付款條件": null,
    "Q'ty Allowance%": null,
    "包裝資訊": null,
    "Reports": null,
    "允收量%": null,
    "索取報告": null,
    "舊系統備註": " Fedex Acct #362944325\n\n\nMako Transport Co., Ltd.\n7F-2, No. 155, Sec. 1, Keelung Rd.,Taipei Taiwan \nTel: 886-2-2528-7272 ext 355\nFax: 886-2-2528-7373\nE-mail :      demi-sung@makotrans.com.tw \nWebsite :   www.makotrans.com.tw\n\nIn future, please send your initial e-mail to cbcisf@cbclogistics.com\nAccounting Department <accounting@theboltbin.com>\n\nPlease add Tami at accounting@theboltbin.com to all invoice and packing slip emails.\n\n*** Going forward can you please include Jordan on all shipping and billing emails. Jordan is in charge of our accounting department and will be better reached at his email. Please include his email on notifications like this going forward, especially invoices.  jordan.vanderkolk@wmtsinc.com.\n"
  },
  {
    "客戶編號": "W009",
    "使用集團設定": null,
    "集團包裝要求(代入)": null,
    "訂單包裝要求(顯示)": null,
    "客戶簡稱": "Wurth(W009)",
    "報告email": null,
    "客戶包裝要求": null,
    "客戶集團代號": null,
    "負責業務": null,
    "分部位置": null,
    "幣別": null,
    "客戶全名": "Wurth Industrial US, Inc.(W009 MN)",
    "匯率": null,
    "客戶地址": "9485 Winnetka Avenue,North Brooklyn Park,\nMN 55445 USA",
    "付款日期": null,
    "客戶電話": "763-424-3374",
    "發票地址": null,
    "客戶傳真": "763-493-027",
    "invoice Email": null,
    "供應商電話": null,
    "供應商傳真": null,
    "客人負責人": null,
    "客人聯絡人": null,
    "供應商聯絡人": null,
    "客人採購": null,
    "客人業務": null,
    "負責船務": null,
    "標籤": null,
    "棧板格式": null,
    "出歐洲 CBAMnote": null,
    "SC shipping  mark": null,
    "紙箱格式": null,
    "Ship to add.": null,
    "整箱重量 max": null,
    "Payment term": null,
    "交貨條件": null,
    "Packing info": null,
    "付款條件": null,
    "Q'ty Allowance%": null,
    "包裝資訊": null,
    "Reports": null,
    "允收量%": null,
    "索取報告": null,
    "舊系統備註": "UPS account # X05502\nBOOKING:3548 Asia Pacific <asia-pacific@wurth-logistics.com>\nCERT IS SENT TO : certs@wurthadams.com\nQuality Assurance Inspector:Destinee Mashl [mailto:DMashl@wurthadams.com] \nThis email address ap@wurthadams.com is for WURTH ADAMS invoices only.\nAccounts Payable (ap@wurthsnider.com\n\nPlease add Tami at accounting@theboltbin.com to all invoice and packing slip emails.\n\n*** Going forward can you please include Jordan on all shipping and billing emails. Jordan is in charge of our accounting department and will be better reached at his email. Please include his email on notifications like this going forward, especially invoices.  jordan.vanderkolk@wmtsinc.com.\n"
  },
  {
    "客戶編號": "W008",
    "使用集團設定": null,
    "集團包裝要求(代入)": null,
    "訂單包裝要求(顯示)": null,
    "客戶簡稱": "Thomas",
    "報告email": null,
    "客戶包裝要求": null,
    "客戶集團代號": null,
    "負責業務": null,
    "分部位置": null,
    "幣別": null,
    "客戶全名": "Thomas Warburton Pty Ltd",
    "匯率": null,
    "客戶地址": "16-26 Dunlop Road \nP.O. Box 566 \nMulgrave, Victoria 3170 \nAUSTRALIA",
    "付款日期": null,
    "客戶電話": "+61 395 743 400",
    "發票地址": null,
    "客戶傳真": "+61 395 743 481",
    "invoice Email": "Tom.Eertman@wuerth-industrie.com",
    "供應商電話": null,
    "供應商傳真": null,
    "客人負責人": null,
    "客人聯絡人": "Tom",
    "供應商聯絡人": null,
    "客人採購": null,
    "客人業務": null,
    "負責船務": null,
    "標籤": null,
    "棧板格式": null,
    "出歐洲 CBAMnote": null,
    "SC shipping  mark": null,
    "紙箱格式": null,
    "Ship to add.": null,
    "整箱重量 max": null,
    "Payment term": null,
    "交貨條件": null,
    "Packing info": null,
    "付款條件": null,
    "Q'ty Allowance%": null,
    "包裝資訊": null,
    "Reports": null,
    "允收量%": null,
    "索取報告": null,
    "舊系統備註": null
  },
  {
    "客戶編號": "W007",
    "使用集團設定": null,
    "集團包裝要求(代入)": null,
    "訂單包裝要求(顯示)": null,
    "客戶簡稱": "Warmingt",
    "報告email": null,
    "客戶包裝要求": null,
    "客戶集團代號": null,
    "負責業務": null,
    "分部位置": null,
    "幣別": null,
    "客戶全名": "WARMINGTON INDUSTRIES",
    "匯率": null,
    "客戶地址": "1336 FRONT AVE NW GRAND RAPIDS, MI 49504, U.S.A.\nATTN:KEENON GOOSEN\nTEL:616 4583815\n\n",
    "付款日期": null,
    "客戶電話": "616-458-3815",
    "發票地址": null,
    "客戶傳真": "616-458-8352",
    "invoice Email": null,
    "供應商電話": null,
    "供應商傳真": null,
    "客人負責人": "Keenon Goosen",
    "客人聯絡人": null,
    "供應商聯絡人": null,
    "客人採購": null,
    "客人業務": null,
    "負責船務": null,
    "標籤": null,
    "棧板格式": null,
    "出歐洲 CBAMnote": null,
    "SC shipping  mark": null,
    "紙箱格式": null,
    "Ship to add.": null,
    "整箱重量 max": null,
    "Payment term": null,
    "交貨條件": null,
    "Packing info": null,
    "付款條件": null,
    "Q'ty Allowance%": null,
    "包裝資訊": null,
    "Reports": null,
    "允收量%": null,
    "索取報告": null,
    "舊系統備註": "2019.07.26 ACCOUNT PERSON: Rita Gainor [mailto:rgainor@warmington.net] \nWarmington Industries FEDEX account number 109616540.\n\nSPA INTERNATIONAL INC.   達豐\n--------------------------------------\nTel: 886-2-25178999 ext.365  \/ext.366   沈'r\nFax: 886-2-25175889\nmail: lory@spa-global.com   陳's\nwebsite: http:\/\/www.spa-global.com\nbooking@spa-global.com"
  },
  {
    "客戶編號": "W006",
    "使用集團設定": null,
    "集團包裝要求(代入)": null,
    "訂單包裝要求(顯示)": null,
    "客戶簡稱": "Wurth(W006)",
    "報告email": null,
    "客戶包裝要求": null,
    "客戶集團代號": null,
    "負責業務": null,
    "分部位置": null,
    "幣別": null,
    "客戶全名": "Wurth Industrie Service Gmbh & Co.KG(W006)",
    "匯率": null,
    "客戶地址": "DRILLBERG 97980 BAD MERGENTHEIM GERMANY\r\nDE275151243",
    "付款日期": null,
    "客戶電話": "49 7931 91-1925",
    "發票地址": null,
    "客戶傳真": "49 7931 91-4000",
    "invoice Email": "roman.batt@wuerth-industrie.com",
    "供應商電話": null,
    "供應商傳真": null,
    "客人負責人": null,
    "客人聯絡人": null,
    "供應商聯絡人": null,
    "客人採購": null,
    "客人業務": null,
    "負責船務": null,
    "標籤": null,
    "棧板格式": null,
    "出歐洲 CBAMnote": null,
    "SC shipping  mark": null,
    "紙箱格式": null,
    "Ship to add.": null,
    "整箱重量 max": null,
    "Payment term": null,
    "交貨條件": null,
    "Packing info": null,
    "付款條件": null,
    "Q'ty Allowance%": null,
    "包裝資訊": null,
    "Reports": null,
    "允收量%": null,
    "索取報告": null,
    "舊系統備註": "supplier number 119896\r\n\r\nWuerth Logistics office in Bremen, Germany: we are right now moving to a new office!\r\nFrom tomorrow on, 12th of April 2024, you will find us here:\r\nWuerth Logistics Deutschland GmbH\r\nKonsul-Smidt-Str. 8r\r\n28217 Bremen\r\nGERMANY\r\n\r\n台灣wurth \r\n2021.01.15\r\nUPS (Express Saver Service mode) Express Saver Service\r\nUPS account number 6090F4 \r\nOur new address will be:\r\n2F., No. 17, Ln. 522, Rongzong Rd., Zuoying Dist., Kaohsiung City, 813 Taiwan.\r\nAnd our new telephone number: +886 7 359 5155  vincent ext 505 手機: 0980 771 545\r\n813 高雄市左營區榮總路522巷17號2樓\r\nPlease be informed that there are two addresses for you to send parcels to us:\r\nFastener samples(扣件類樣品):\r\nNo. 16, Lane 526, Rongzong Rd., Zuoying Dist., Kaohsiung City, 813 Taiwan\r\nOthers(其他包裹\/郵件):\r\n2F., No. 17, Ln. 522, Rongzong Rd., Zuoying Dist., Kaohsiung City, 813 Taiwan\r\n2021\/10\/27 INVOICE要發給 invoice@wuerthindustri.se\r\n\r\n2020.11.24 柯同意更改 提單做法上註明：Please issue Sea Waybill to shipper\/consignee & No FCR\r\n2020.11.13 Eckert, Philipp\r\nPlease send the documents per Mail to ISIR@wuerth-industrie.com\r\nSoman, Madhura <Madhura.Soman@wuerth-industrie.com>\r\n2020.09.18 文件都要給:\r\nDeininger, Gerd <Gerd.Deininger@wuerth-industrie.com\r\n\r\n2020.Mar.27\r\nFrom: Soman, Madhura [mailto:Madhura.Soman@wuerth-industrie.com] \r\n寄文件時給,還有文件寄出時 都要 C.C. \r\n@ Asia-Pacific@wurth-logistics.com\r\nanja.hoffmann@wurth-logistics.com\r\nGerd.Deininger@wuerth-industrie.com (另外運費cotnact to Gerd directly with WIS  ) \r\n\r\n2019.10.09\r\n**********\r\nFrom: Shrutika Ware [mailto:Shrutika.Ware@wuerth-industry.in] \r\nSent: Tuesday, October 8, 2019 8:19 PM\r\nTo: janeke@locksure.com.tw; Asia Pacific <Asia-Pacific@wurth-logistics.com>\r\nSubject: 6000257815\r\n\r\ncould you please send bill of lading for attached invoice directly to Asia Pacific\r\n Asia-Pacific@wurth-logistics.com\r\n\r\n2019.03.26 BOOKING:\r\nHans Gomes \r\nSupply Chain Optimizer \r\nWurth Logistics Asia-Pacific Sdn. Bhd. (1191000-X) \r\nLot 806, Jalan Subang 5  Taman Perindustrian Subang  47600 Subang Jaya  Selangor, Malaysia \r\nT +60 3 8021 0176 \r\nhans.gomes@wurth-logistics.com \r\n\r\n\r\n\r\nYour login name is: jke\r\n密碼已變更為   21236122\r\nThe Integratix platform can be accessed via the following link: https:\/\/www.integratix.de\r\n\r\nPay attention to correct case of login name and password.\r\nFor security reasons, please change your password via the menu option \"Settings\" -> \"My Account\".\r\n\r\npallet 供應商: \r\n東昕  陳s  0929750810  \r\nfax no. 6125055"
  },
  {
    "客戶編號": "W005",
    "使用集團設定": null,
    "集團包裝要求(代入)": null,
    "訂單包裝要求(顯示)": null,
    "客戶簡稱": "Wilms",
    "報告email": null,
    "客戶包裝要求": null,
    "客戶集團代號": null,
    "負責業務": null,
    "分部位置": null,
    "幣別": null,
    "客戶全名": "Wilms  NV",
    "匯率": null,
    "客戶地址": "Attention of E. WILMS \/ F.Kums\nMolsebaan 20 B-2450 Meerhout\nBelgium",
    "付款日期": null,
    "客戶電話": "32 14 36 99 70",
    "發票地址": null,
    "客戶傳真": "32 14 30 96 47",
    "invoice Email": " fkums@scarlet.be",
    "供應商電話": null,
    "供應商傳真": null,
    "客人負責人": null,
    "客人聯絡人": null,
    "供應商聯絡人": null,
    "客人採購": null,
    "客人業務": null,
    "負責船務": null,
    "標籤": null,
    "棧板格式": null,
    "出歐洲 CBAMnote": null,
    "SC shipping  mark": null,
    "紙箱格式": null,
    "Ship to add.": null,
    "整箱重量 max": null,
    "Payment term": null,
    "交貨條件": null,
    "Packing info": null,
    "付款條件": null,
    "Q'ty Allowance%": null,
    "包裝資訊": null,
    "Reports": null,
    "允收量%": null,
    "索取報告": null,
    "舊系統備註": "AGENT : FRANS KUMS  CELL PHONE ; 002-32-477 73  56 - 46"
  },
  {
    "客戶編號": "W004",
    "使用集團設定": null,
    "集團包裝要求(代入)": null,
    "訂單包裝要求(顯示)": null,
    "客戶簡稱": "WESTINOX",
    "報告email": null,
    "客戶包裝要求": null,
    "客戶集團代號": null,
    "負責業務": null,
    "分部位置": null,
    "幣別": null,
    "客戶全名": "WESTINOX INTERNATIONAL N.V.",
    "匯率": null,
    "客戶地址": "ST.KATHARINASTRAAT 95\nB-8501 KORTRIJK-HEULE\nBELGIUM",
    "付款日期": null,
    "客戶電話": "056 357207",
    "發票地址": null,
    "客戶傳真": "056 370351",
    "invoice Email": null,
    "供應商電話": null,
    "供應商傳真": null,
    "客人負責人": null,
    "客人聯絡人": "L.NAESSENS",
    "供應商聯絡人": null,
    "客人採購": null,
    "客人業務": null,
    "負責船務": null,
    "標籤": null,
    "棧板格式": null,
    "出歐洲 CBAMnote": null,
    "SC shipping  mark": null,
    "紙箱格式": null,
    "Ship to add.": null,
    "整箱重量 max": null,
    "Payment term": null,
    "交貨條件": null,
    "Packing info": null,
    "付款條件": null,
    "Q'ty Allowance%": null,
    "包裝資訊": null,
    "Reports": null,
    "允收量%": null,
    "索取報告": null,
    "舊系統備註": null
  },
  {
    "客戶編號": "W003",
    "使用集團設定": null,
    "集團包裝要求(代入)": null,
    "訂單包裝要求(顯示)": null,
    "客戶簡稱": "WASI",
    "報告email": null,
    "客戶包裝要求": null,
    "客戶集團代號": null,
    "負責業務": null,
    "分部位置": null,
    "幣別": null,
    "客戶全名": "WAGENER & SIMON. WASI GMBH & CO. KG",
    "匯率": null,
    "客戶地址": "ERWINSTR. 2\n42289 WUPPERTAL\nGERMANY",
    "付款日期": null,
    "客戶電話": "49-202-263-2272",
    "發票地址": null,
    "客戶傳真": "49-202-263-2373",
    "invoice Email": "joerg.kuchl@wasi.de",
    "供應商電話": null,
    "供應商傳真": null,
    "客人負責人": null,
    "客人聯絡人": "HERR KUEHL",
    "供應商聯絡人": null,
    "客人採購": null,
    "客人業務": null,
    "負責船務": null,
    "標籤": null,
    "棧板格式": null,
    "出歐洲 CBAMnote": null,
    "SC shipping  mark": null,
    "紙箱格式": null,
    "Ship to add.": null,
    "整箱重量 max": null,
    "Payment term": null,
    "交貨條件": null,
    "Packing info": null,
    "付款條件": null,
    "Q'ty Allowance%": null,
    "包裝資訊": null,
    "Reports": null,
    "允收量%": null,
    "索取報告": null,
    "舊系統備註": "出貨文件  - 請參閱出貨文件檔\n1. 客戶盒裝標籤圖樣"
  },
  {
    "客戶編號": "W002",
    "使用集團設定": null,
    "集團包裝要求(代入)": null,
    "訂單包裝要求(顯示)": null,
    "客戶簡稱": "KELLNER",
    "報告email": null,
    "客戶包裝要求": null,
    "客戶集團代號": null,
    "負責業務": null,
    "分部位置": null,
    "幣別": null,
    "客戶全名": "W. KELLNER HANDELSGEASLLSCHAFT MBH",
    "匯率": null,
    "客戶地址": "GEISELBERGSTRABE\n10-12, 1111 WLEN\nAUSTRIA",
    "付款日期": null,
    "客戶電話": "43-1-797-700",
    "發票地址": null,
    "客戶傳真": "43-1-797-7061",
    "invoice Email": null,
    "供應商電話": null,
    "供應商傳真": null,
    "客人負責人": null,
    "客人聯絡人": "FUGGER",
    "供應商聯絡人": null,
    "客人採購": null,
    "客人業務": null,
    "負責船務": null,
    "標籤": null,
    "棧板格式": null,
    "出歐洲 CBAMnote": null,
    "SC shipping  mark": null,
    "紙箱格式": null,
    "Ship to add.": null,
    "整箱重量 max": null,
    "Payment term": null,
    "交貨條件": null,
    "Packing info": null,
    "付款條件": null,
    "Q'ty Allowance%": null,
    "包裝資訊": null,
    "Reports": null,
    "允收量%": null,
    "索取報告": null,
    "舊系統備註": null
  },
  {
    "客戶編號": "W001",
    "使用集團設定": null,
    "集團包裝要求(代入)": null,
    "訂單包裝要求(顯示)": null,
    "客戶簡稱": "WERMA",
    "報告email": null,
    "客戶包裝要求": null,
    "客戶集團代號": null,
    "負責業務": null,
    "分部位置": null,
    "幣別": null,
    "客戶全名": "WERMA COMPUTER SECURITY",
    "匯率": null,
    "客戶地址": "14 SPOORSTRAAT, 4431 NK 'S-GRAVENPOLDER\nP.O.BOX 57, 4430 AB 'S-GRAVENPOLDER\nTHE NETHERLANDS",
    "付款日期": null,
    "客戶電話": "31-113-311-324",
    "發票地址": null,
    "客戶傳真": "31-113-312-382",
    "invoice Email": null,
    "供應商電話": null,
    "供應商傳真": null,
    "客人負責人": null,
    "客人聯絡人": "WIM JANSEN",
    "供應商聯絡人": null,
    "客人採購": null,
    "客人業務": null,
    "負責船務": null,
    "標籤": null,
    "棧板格式": null,
    "出歐洲 CBAMnote": null,
    "SC shipping  mark": null,
    "紙箱格式": null,
    "Ship to add.": null,
    "整箱重量 max": null,
    "Payment term": null,
    "交貨條件": null,
    "Packing info": null,
    "付款條件": null,
    "Q'ty Allowance%": null,
    "包裝資訊": null,
    "Reports": null,
    "允收量%": null,
    "索取報告": null,
    "舊系統備註": "\n1. 出貨文件: 請參閱出貨文件檔"
  },
  {
    "客戶編號": "V901",
    "使用集團設定": null,
    "集團包裝要求(代入)": null,
    "訂單包裝要求(顯示)": null,
    "客戶簡稱": "唯文",
    "報告email": null,
    "客戶包裝要求": null,
    "客戶集團代號": null,
    "負責業務": null,
    "分部位置": null,
    "幣別": null,
    "客戶全名": "唯文股份有限公司",
    "匯率": null,
    "客戶地址": "高雄縣岡山鎮岡山北路15號\n\n",
    "付款日期": null,
    "客戶電話": "07-6221177",
    "發票地址": null,
    "客戶傳真": "07-6221188",
    "invoice Email": null,
    "供應商電話": null,
    "供應商傳真": null,
    "客人負責人": "呂文水",
    "客人聯絡人": "呂文水",
    "供應商聯絡人": null,
    "客人採購": null,
    "客人業務": null,
    "負責船務": null,
    "標籤": null,
    "棧板格式": null,
    "出歐洲 CBAMnote": null,
    "SC shipping  mark": null,
    "紙箱格式": null,
    "Ship to add.": null,
    "整箱重量 max": null,
    "Payment term": null,
    "交貨條件": null,
    "Packing info": null,
    "付款條件": null,
    "Q'ty Allowance%": null,
    "包裝資訊": null,
    "Reports": null,
    "允收量%": null,
    "索取報告": null,
    "舊系統備註": null
  },
  {
    "客戶編號": "V010",
    "使用集團設定": null,
    "集團包裝要求(代入)": null,
    "訂單包裝要求(顯示)": null,
    "客戶簡稱": "VGV",
    "報告email": null,
    "客戶包裝要求": null,
    "客戶集團代號": null,
    "負責業務": null,
    "分部位置": null,
    "幣別": null,
    "客戶全名": "VGV.s.r.l",
    "匯率": null,
    "客戶地址": "Sede Operativa Via Isorella, 49\/51 − 25012 Calvisano (BS) − ITALY\n\n",
    "付款日期": null,
    "客戶電話": "+39 030 6951677",
    "發票地址": null,
    "客戶傳真": "+39 030 9934372",
    "invoice Email": "fabio.alessandroni@vgvsrl.com",
    "供應商電話": null,
    "供應商傳真": null,
    "客人負責人": null,
    "客人聯絡人": "Fabio Alessandroni",
    "供應商聯絡人": null,
    "客人採購": null,
    "客人業務": null,
    "負責船務": null,
    "標籤": null,
    "棧板格式": null,
    "出歐洲 CBAMnote": null,
    "SC shipping  mark": null,
    "紙箱格式": null,
    "Ship to add.": null,
    "整箱重量 max": null,
    "Payment term": null,
    "交貨條件": null,
    "Packing info": null,
    "付款條件": null,
    "Q'ty Allowance%": null,
    "包裝資訊": null,
    "Reports": null,
    "允收量%": null,
    "索取報告": null,
    "舊系統備註": "2024.11.06 報告寄: IF REQUIRED PLEASE SEND THE CERTIFICATION TO THE EMIL ADDRESS: CERTIFICATI@VGVSRL.COM"
  },
  {
    "客戶編號": "V009",
    "使用集團設定": null,
    "集團包裝要求(代入)": null,
    "訂單包裝要求(顯示)": null,
    "客戶簡稱": "VIKING",
    "報告email": null,
    "客戶包裝要求": null,
    "客戶集團代號": null,
    "負責業務": null,
    "分部位置": null,
    "幣別": null,
    "客戶全名": "VIKING PRODUCTS,INC.",
    "匯率": null,
    "客戶地址": "3260 Northridge Drive NW\r\nGrand Rapids, Michigan 49544 USA\r\n",
    "付款日期": null,
    "客戶電話": "616 791 2277",
    "發票地址": null,
    "客戶傳真": "616 791 7999",
    "invoice Email": null,
    "供應商電話": null,
    "供應商傳真": null,
    "客人負責人": null,
    "客人聯絡人": null,
    "供應商聯絡人": null,
    "客人採購": null,
    "客人業務": null,
    "負責船務": null,
    "標籤": null,
    "棧板格式": "LAREDO,TX\r\nPART NO.:\r\nP\/NO.  \r\nMADE IN TAIWAN",
    "出歐洲 CBAMnote": null,
    "SC shipping  mark": "LAREDO,TX\r\nPART NO.:\r\nC\/NO.\r\nMADE IN TAIWAN",
    "紙箱格式": "*** 如附件 ***",
    "Ship to add.": "EXPEDITORS CALLE PLOMEROS NO 145 – A ZONA INDUSTRIAL, SAN LUIS POTOSÍ\r\n          SAN LUIS POTOSI SLP 78395 MEXICO      CONTACT: ERIKA MUNOZ",
    "整箱重量 max": null,
    "Payment term": "BY T\/T,30 DAYS AFTER SETTING COPY BILL OF LADING",
    "交貨條件": "FOR KAOHSIUNG",
    "Packing info": "BY EXPORT CARTON THEN PALLETIZED - PALLET:80 X 80cm   250PCS\/BOX",
    "付款條件": "BY 10 DAYS CHECK AFTER SHIPMENT",
    "Q'ty Allowance%": "QUANTITY ALLOWANCE PLUS 10% \/ MINUS 10%",
    "包裝資訊": "BY EXPORT CARTON THEN PALLETIZED-請告知墊板內紙箱編號(熱處理墊板)\r\n             PALLET:80 X 80cm 美規墊板  250PCS\/BOX\r\n            **** 滿箱\/滿板出貨 不可有尾數箱  *****\r\n            包裝:無需上黃色塑膠打包帶.每一外箱只要粘貼條碼貼紙於大嘜正中間\r\n            紙箱需依客人規定之規格及標示客戶LOGO(詳細內容請見附件)\r\n            請連繫永豐餘-柯先生\/佑丞-郭先生\/振隆-鄭先生\r\n            棧板包裝:四邊都要上腳柱,己防產品被壓破.壓壞.\r\n            PALLET-墊板上 出貨前 需噴槍 再噴一下 種子 棉絮等 清乾淨 \r\n            出口木質包裝材料(WPM),請依國際植物檢疫措施第15條(ISPM15)規定完成檢疫處理,並加蓋\"檢疫處理戳章\"",
    "Reports": "MATERIAL CERTIFICATION & INSPECTED REPORT REQUIRED & PLATING CERTS",
    "允收量%": "QUANTITY ALLOWANCE PLUS 5% \/ MINUS 5%",
    "索取報告": "樣品.出貨請附件驗報告, 材質證明, 硬度報告, 篩選報告",
    "舊系統備註": "DHL Our account# 962174485\r\nFEDEX OUR ACCOUNT# 237474767\r\nUPS#10F198\r\n\r\nReport: 'quality@vikingproducts.com'\r\n\r\nLeah Chi（許雅琪） Manager - Asia Pacific Regional \r\nCell:  +011 886 (0) 963 272 625 (06-202-6483) \r\nLINE: Leah ( ID : 0963 272 625)\r\nPHONE:06 202 6483\r\n \r\n*** invoices need to be sent to Accounting (ap@vikingproducts.com)\r\n\r\n出貨文件給: \r\n'ap@vikingproducts.com'; 'materials@vikingproducts.com'\r\n\r\n訂單系統: https:\/\/www.plexus-online.com\/signon\r\n1.Viking\r\n2.KHUANG.VP\r\n3.20190904##@&\r\n\r\nCOMPANY CODE:viking\r\nUsername:  jke.vp\r\nPassword:  locksure95\r\n\r\n用戶帳號:viking\r\n船務只使用系統裡的 online release\r\n\r\nLeah Chi（許雅琪）\r\nManager - Asia Pacific Regional \r\nNo. 257, Yongming St., Yongkang Dist., \r\nTainan City 710, Taiwan (R.O.C)\r\nCell:  +011 886 (0) 963 272 625\r\nLINE: Leah ( ID : 0963 272 625)\r\nE-Mail: lchi@vikingproducts.com.tw\r\nWebsite: www.vikingproducts.com \r\n06 - 2026483\r\n \r\nRelease Types and Definitions;\r\n\r\n1) HOLD - RELEASE ON HOLD DO NOT PRODUCE WITHOUT AUTHORIZATION\r\n2) OTW - PENDING - RELEASES THAT HAVE SHIPPED TO THE FORWARDER\/PORT\r\n3) OTW - SHIPPED - RELEASES THAT ARE CONFIRMED FOR SHIPMENT ON THE BOAT\r\n4) RAW MATERIAL AUTHORIZATION - RELEASES FOR AUTHORIZATION TO PROCURE MATERIAL ONLY.  DO NOT PRODUCE FINAL PRODUCT.\r\n5) NEAR EOP CONFIRM PRIOR TO PROD - RELEASES NEARING THE END OF PRODUCTION.  PRIOR TO PRODUCTION OF FINAL GOODS AUTHORIZATION REQUIRED.  QUANTITY OR DUE DATE COULD CHANGE.\r\n6) FIRM - RELEASE THAT ARE CONFIRMED TO PRODUCE (WITHIN 6 WEEKS PRIOR TO SHIP DATE)\r\n7) CANCELLED - RELEASES THAT ARE NO LONGER REQUIRED."
  },
  {
    "客戶編號": "V008",
    "使用集團設定": null,
    "集團包裝要求(代入)": null,
    "訂單包裝要求(顯示)": null,
    "客戶簡稱": "VIORAL",
    "報告email": null,
    "客戶包裝要求": null,
    "客戶集團代號": null,
    "負責業務": null,
    "分部位置": null,
    "幣別": null,
    "客戶全名": "VIORAL",
    "匯率": null,
    "客戶地址": "NATO AV, NEA ZOI, 19300 ASPROPYRGOS,\nPO. 83 GREECE\n",
    "付款日期": null,
    "客戶電話": "30 210 55 96 525",
    "發票地址": null,
    "客戶傳真": "30 210 55 96 531",
    "invoice Email": "sinis@vioral.com",
    "供應商電話": null,
    "供應商傳真": null,
    "客人負責人": null,
    "客人聯絡人": null,
    "供應商聯絡人": null,
    "客人採購": null,
    "客人業務": null,
    "負責船務": null,
    "標籤": null,
    "棧板格式": null,
    "出歐洲 CBAMnote": null,
    "SC shipping  mark": null,
    "紙箱格式": null,
    "Ship to add.": null,
    "整箱重量 max": null,
    "Payment term": null,
    "交貨條件": null,
    "Packing info": null,
    "付款條件": null,
    "Q'ty Allowance%": null,
    "包裝資訊": null,
    "Reports": null,
    "允收量%": null,
    "索取報告": null,
    "舊系統備註": "DHL account number 965109853\n\nWinifred Lan (藍文君) - Mediterranean\nOriental Power Logistics Co., Ltd.\n曜 捷 運 通 有 限 公 司\nTEL: +886-2-2523 5168  Ext.709\nFAX: +886-2-2561 8021\nE-mail: winifred_lan@opl.com.tw\n\n"
  },
  {
    "客戶編號": "V007",
    "使用集團設定": null,
    "集團包裝要求(代入)": null,
    "訂單包裝要求(顯示)": null,
    "客戶簡稱": "VOSWINKE",
    "報告email": null,
    "客戶包裝要求": null,
    "客戶集團代號": null,
    "負責業務": null,
    "分部位置": null,
    "幣別": null,
    "客戶全名": "VOSWINKEL GMBH",
    "匯率": null,
    "客戶地址": "NEUGRUNENTHAL D-58540 MEINERZHAGEN\nGERMANY\n",
    "付款日期": null,
    "客戶電話": "49(0)2354\/705-140",
    "發票地址": null,
    "客戶傳真": "49(0)2354\/705-159",
    "invoice Email": null,
    "供應商電話": null,
    "供應商傳真": null,
    "客人負責人": null,
    "客人聯絡人": null,
    "供應商聯絡人": null,
    "客人採購": null,
    "客人業務": null,
    "負責船務": null,
    "標籤": null,
    "棧板格式": null,
    "出歐洲 CBAMnote": null,
    "SC shipping  mark": null,
    "紙箱格式": null,
    "Ship to add.": null,
    "整箱重量 max": null,
    "Payment term": null,
    "交貨條件": null,
    "Packing info": null,
    "付款條件": null,
    "Q'ty Allowance%": null,
    "包裝資訊": null,
    "Reports": null,
    "允收量%": null,
    "索取報告": null,
    "舊系統備註": null
  },
  {
    "客戶編號": "V006",
    "使用集團設定": null,
    "集團包裝要求(代入)": null,
    "訂單包裝要求(顯示)": null,
    "客戶簡稱": "VERINOX",
    "報告email": null,
    "客戶包裝要求": null,
    "客戶集團代號": null,
    "負責業務": null,
    "分部位置": null,
    "幣別": null,
    "客戶全名": "VERINOX FASTNERS AND PARTS",
    "匯率": null,
    "客戶地址": "\n\n",
    "付款日期": null,
    "客戶電話": null,
    "發票地址": null,
    "客戶傳真": null,
    "invoice Email": null,
    "供應商電話": null,
    "供應商傳真": null,
    "客人負責人": null,
    "客人聯絡人": null,
    "供應商聯絡人": null,
    "客人採購": null,
    "客人業務": null,
    "負責船務": null,
    "標籤": null,
    "棧板格式": null,
    "出歐洲 CBAMnote": null,
    "SC shipping  mark": null,
    "紙箱格式": null,
    "Ship to add.": null,
    "整箱重量 max": null,
    "Payment term": null,
    "交貨條件": null,
    "Packing info": null,
    "付款條件": null,
    "Q'ty Allowance%": null,
    "包裝資訊": null,
    "Reports": null,
    "允收量%": null,
    "索取報告": null,
    "舊系統備註": null
  },
  {
    "客戶編號": "V005",
    "使用集團設定": null,
    "集團包裝要求(代入)": null,
    "訂單包裝要求(顯示)": null,
    "客戶簡稱": "VERYFAST",
    "報告email": null,
    "客戶包裝要求": null,
    "客戶集團代號": null,
    "負責業務": null,
    "分部位置": null,
    "幣別": null,
    "客戶全名": "VERYFASTENERS LIMITED",
    "匯率": null,
    "客戶地址": "BROMFORD LANE\nWEST BROMWICH\nWEST MIDLANDS B70 7JJ U.K.",
    "付款日期": null,
    "客戶電話": "44 121 580 0518",
    "發票地址": null,
    "客戶傳真": "44-121 580 9966",
    "invoice Email": null,
    "供應商電話": null,
    "供應商傳真": null,
    "客人負責人": null,
    "客人聯絡人": "JOHN PARTRIDGE",
    "供應商聯絡人": null,
    "客人採購": null,
    "客人業務": null,
    "負責船務": null,
    "標籤": null,
    "棧板格式": null,
    "出歐洲 CBAMnote": null,
    "SC shipping  mark": null,
    "紙箱格式": null,
    "Ship to add.": null,
    "整箱重量 max": null,
    "Payment term": null,
    "交貨條件": null,
    "Packing info": null,
    "付款條件": null,
    "Q'ty Allowance%": null,
    "包裝資訊": null,
    "Reports": null,
    "允收量%": null,
    "索取報告": null,
    "舊系統備註": "WORKS MOBILE 07989 480007\n "
  },
  {
    "客戶編號": "V004",
    "使用集團設定": null,
    "集團包裝要求(代入)": null,
    "訂單包裝要求(顯示)": null,
    "客戶簡稱": "VISSERIE",
    "報告email": null,
    "客戶包裝要求": null,
    "客戶集團代號": null,
    "負責業務": null,
    "分部位置": null,
    "幣別": null,
    "客戶全名": "VISSERIE V.B.R.\/JOPI",
    "匯率": null,
    "客戶地址": "Z.I. LA FORET 73240\nSAINT GENIX SUR GUIERS\nFRANCE",
    "付款日期": null,
    "客戶電話": "002-33-4-76-32-56-00",
    "發票地址": null,
    "客戶傳真": "00 44 121 580 9966.",
    "invoice Email": null,
    "供應商電話": null,
    "供應商傳真": null,
    "客人負責人": null,
    "客人聯絡人": "PUERRE",
    "供應商聯絡人": null,
    "客人採購": null,
    "客人業務": null,
    "負責船務": null,
    "標籤": null,
    "棧板格式": null,
    "出歐洲 CBAMnote": null,
    "SC shipping  mark": null,
    "紙箱格式": null,
    "Ship to add.": null,
    "整箱重量 max": null,
    "Payment term": null,
    "交貨條件": null,
    "Packing info": null,
    "付款條件": null,
    "Q'ty Allowance%": null,
    "包裝資訊": null,
    "Reports": null,
    "允收量%": null,
    "索取報告": null,
    "舊系統備註": null
  },
  {
    "客戶編號": "V003",
    "使用集團設定": null,
    "集團包裝要求(代入)": null,
    "訂單包裝要求(顯示)": null,
    "客戶簡稱": "VITERIA",
    "報告email": null,
    "客戶包裝要求": null,
    "客戶集團代號": null,
    "負責業務": null,
    "分部位置": null,
    "幣別": null,
    "客戶全名": "VITERIA EUGANEA S.R.L",
    "匯率": null,
    "客戶地址": "VIA EMILIA ROMAGNA, 44\/46\n35929 SANONARA ( PADOVA )\nITALY",
    "付款日期": null,
    "客戶電話": "31-49-64-44-11",
    "發票地址": null,
    "客戶傳真": "31-49-64-49-78",
    "invoice Email": null,
    "供應商電話": null,
    "供應商傳真": null,
    "客人負責人": null,
    "客人聯絡人": "G.GUZZO",
    "供應商聯絡人": null,
    "客人採購": null,
    "客人業務": null,
    "負責船務": null,
    "標籤": null,
    "棧板格式": null,
    "出歐洲 CBAMnote": null,
    "SC shipping  mark": null,
    "紙箱格式": null,
    "Ship to add.": null,
    "整箱重量 max": null,
    "Payment term": null,
    "交貨條件": null,
    "Packing info": null,
    "付款條件": null,
    "Q'ty Allowance%": null,
    "包裝資訊": null,
    "Reports": null,
    "允收量%": null,
    "索取報告": null,
    "舊系統備註": null
  },
  {
    "客戶編號": "V002",
    "使用集團設定": null,
    "集團包裝要求(代入)": null,
    "訂單包裝要求(顯示)": null,
    "客戶簡稱": "VIA",
    "報告email": null,
    "客戶包裝要求": null,
    "客戶集團代號": null,
    "負責業務": null,
    "分部位置": null,
    "幣別": null,
    "客戶全名": "VIA PACIFIC, INC.",
    "匯率": null,
    "客戶地址": "738 S. EPPERSON DRIVE\nCITY OF INDUSTRY, CA 91748\nU.S.A",
    "付款日期": null,
    "客戶電話": "1-626-810-8881",
    "發票地址": null,
    "客戶傳真": "1-626-810-8861",
    "invoice Email": null,
    "供應商電話": null,
    "供應商傳真": null,
    "客人負責人": null,
    "客人聯絡人": "YIU",
    "供應商聯絡人": null,
    "客人採購": null,
    "客人業務": null,
    "負責船務": null,
    "標籤": null,
    "棧板格式": null,
    "出歐洲 CBAMnote": null,
    "SC shipping  mark": null,
    "紙箱格式": null,
    "Ship to add.": null,
    "整箱重量 max": null,
    "Payment term": null,
    "交貨條件": null,
    "Packing info": null,
    "付款條件": null,
    "Q'ty Allowance%": null,
    "包裝資訊": null,
    "Reports": null,
    "允收量%": null,
    "索取報告": null,
    "舊系統備註": null
  },
  {
    "客戶編號": "V001",
    "使用集團設定": null,
    "集團包裝要求(代入)": null,
    "訂單包裝要求(顯示)": null,
    "客戶簡稱": "VALVULAS",
    "報告email": null,
    "客戶包裝要求": null,
    "客戶集團代號": null,
    "負責業務": null,
    "分部位置": null,
    "幣別": null,
    "客戶全名": "VALVULAS WORCESTER DE MEXICO, S.A. DE C.V.",
    "匯率": null,
    "客戶地址": "MAIZ NO. 263 COL. VALLE DEL SUR\nG.P. 09819 DELEGACION IZTAPALAPA\nMEXICO. D.F.",
    "付款日期": null,
    "客戶電話": "52-5670-5155",
    "發票地址": null,
    "客戶傳真": "52-5670-6741",
    "invoice Email": null,
    "供應商電話": null,
    "供應商傳真": null,
    "客人負責人": null,
    "客人聯絡人": "MEDINA",
    "供應商聯絡人": null,
    "客人採購": null,
    "客人業務": null,
    "負責船務": null,
    "標籤": null,
    "棧板格式": null,
    "出歐洲 CBAMnote": null,
    "SC shipping  mark": null,
    "紙箱格式": null,
    "Ship to add.": null,
    "整箱重量 max": null,
    "Payment term": null,
    "交貨條件": null,
    "Packing info": null,
    "付款條件": null,
    "Q'ty Allowance%": null,
    "包裝資訊": null,
    "Reports": null,
    "允收量%": null,
    "索取報告": null,
    "舊系統備註": null
  },
  {
    "客戶編號": "U007",
    "使用集團設定": null,
    "集團包裝要求(代入)": null,
    "訂單包裝要求(顯示)": null,
    "客戶簡稱": "UNEEDA",
    "報告email": null,
    "客戶包裝要求": null,
    "客戶集團代號": null,
    "負責業務": null,
    "分部位置": null,
    "幣別": null,
    "客戶全名": "UNEEDA BOLT & SCREW CO. INC.",
    "匯率": null,
    "客戶地址": "10 CAPITOL DRIVE MOONACHIE\nNJ. 07074\nUSA",
    "付款日期": null,
    "客戶電話": "LINDA BRIGGS",
    "發票地址": null,
    "客戶傳真": "0021-201-440-8600",
    "invoice Email": "LindaB@UneedaBolt.com",
    "供應商電話": null,
    "供應商傳真": null,
    "客人負責人": "Keenon Goosen",
    "客人聯絡人": "0021-201-440-7688",
    "供應商聯絡人": null,
    "客人採購": null,
    "客人業務": null,
    "負責船務": null,
    "標籤": null,
    "棧板格式": null,
    "出歐洲 CBAMnote": null,
    "SC shipping  mark": null,
    "紙箱格式": null,
    "Ship to add.": null,
    "整箱重量 max": null,
    "Payment term": null,
    "交貨條件": null,
    "Packing info": null,
    "付款條件": null,
    "Q'ty Allowance%": null,
    "包裝資訊": null,
    "Reports": null,
    "允收量%": null,
    "索取報告": null,
    "舊系統備註": "forwarder:\nT.H.I. GROUP LTD. - TAIWAN OFFICE          台驊                 \n8th FL NO 31 PAO CHIN ST.                                   \nTAIPEI, TW\nTEL# 011-886-2-2753-2093\nFAX# 011-886-2-2765-35127           \nCONTACT: SUNNY 郭  ext.127\n "
  },
  {
    "客戶編號": "U006",
    "使用集團設定": null,
    "集團包裝要求(代入)": null,
    "訂單包裝要求(顯示)": null,
    "客戶簡稱": "UM(U006)",
    "報告email": null,
    "客戶包裝要求": null,
    "客戶集團代號": null,
    "負責業務": null,
    "分部位置": null,
    "幣別": null,
    "客戶全名": "KYOCERA UNIMERCO FASTENING A\/S",
    "匯率": null,
    "客戶地址": "DREJERVEJ 2 POSTBOKS 104\nDK-7451 SUNDS DENMARK\nVAT\/EIN NO.21126543\n",
    "付款日期": null,
    "客戶電話": "002-45-97-1414-11",
    "發票地址": null,
    "客戶傳真": "002-45-97-1414-86",
    "invoice Email": "umdk@unimerco.com",
    "供應商電話": null,
    "供應商傳真": null,
    "客人負責人": null,
    "客人聯絡人": "LARS B. NIELSEN",
    "供應商聯絡人": null,
    "客人採購": null,
    "客人業務": null,
    "負責船務": null,
    "標籤": null,
    "棧板格式": null,
    "出歐洲 CBAMnote": null,
    "SC shipping  mark": null,
    "紙箱格式": null,
    "Ship to add.": null,
    "整箱重量 max": null,
    "Payment term": null,
    "交貨條件": null,
    "Packing info": null,
    "付款條件": null,
    "Q'ty Allowance%": null,
    "包裝資訊": null,
    "Reports": null,
    "允收量%": null,
    "索取報告": null,
    "舊系統備註": "2019.02.14 NEW PERSON\nMichael Mølgaard on copy his email is MIM@kyocera-unimerco.com\nThomas Christensen <tch@kyocera-unimerco.com>\nJEEP -OUT\n\n客戶稽核合格廠商: 聖田\nSHIPMENT CONTACT WITH :  Henrik K Poulsen\" <hkp@unimerco.com>\n\nBon Voyage Express Ltd. 浩閎\n11F-2, No. 51 Sung Chiang Road\nTaipei, Taiwan, R.O.C.\nPh.: 886-2-25097818 ext. 200\nFax: 886-2-25040870, 25023854\nFAX: (02) 2729-6936\n"
  },
  {
    "客戶編號": "U005",
    "使用集團設定": null,
    "集團包裝要求(代入)": null,
    "訂單包裝要求(顯示)": null,
    "客戶簡稱": "UCAF",
    "報告email": null,
    "客戶包裝要求": null,
    "客戶集團代號": null,
    "負責業務": null,
    "分部位置": null,
    "幣別": null,
    "客戶全名": "UNION COMPRASS ALMACENISTAS",
    "匯率": null,
    "客戶地址": "P.I. GUADALHORCE. C\/ESTEBAN SALAZAR\nCHAPELA, 9 P.2 OF.13 OF.COANTARRANAS\n.29004 MALAGA. SPAIN",
    "付款日期": null,
    "客戶電話": "002-34-95-2246972",
    "發票地址": null,
    "客戶傳真": "002-34-95-2240117",
    "invoice Email": null,
    "供應商電話": null,
    "供應商傳真": null,
    "客人負責人": null,
    "客人聯絡人": null,
    "供應商聯絡人": null,
    "客人採購": null,
    "客人業務": null,
    "負責船務": null,
    "標籤": null,
    "棧板格式": null,
    "出歐洲 CBAMnote": null,
    "SC shipping  mark": null,
    "紙箱格式": null,
    "Ship to add.": null,
    "整箱重量 max": null,
    "Payment term": null,
    "交貨條件": null,
    "Packing info": null,
    "付款條件": null,
    "Q'ty Allowance%": null,
    "包裝資訊": null,
    "Reports": null,
    "允收量%": null,
    "索取報告": null,
    "舊系統備註": null
  },
  {
    "客戶編號": "U004",
    "使用集團設定": null,
    "集團包裝要求(代入)": null,
    "訂單包裝要求(顯示)": null,
    "客戶簡稱": "UBN",
    "報告email": null,
    "客戶包裝要求": null,
    "客戶集團代號": null,
    "負責業務": null,
    "分部位置": null,
    "幣別": null,
    "客戶全名": "UNIVERSAL BOLT & NUTS (PTY) LTD.",
    "匯率": null,
    "客戶地址": "288 CHAMBERLAIN ROAD\nJACOBS 4052 DURBAN\nSOUTH AFRICA",
    "付款日期": null,
    "客戶電話": "002-27-31-468-5224",
    "發票地址": null,
    "客戶傳真": "002-27-31-468-6072",
    "invoice Email": null,
    "供應商電話": null,
    "供應商傳真": null,
    "客人負責人": null,
    "客人聯絡人": "LOGAN BILLY",
    "供應商聯絡人": null,
    "客人採購": null,
    "客人業務": null,
    "負責船務": null,
    "標籤": null,
    "棧板格式": null,
    "出歐洲 CBAMnote": null,
    "SC shipping  mark": null,
    "紙箱格式": null,
    "Ship to add.": null,
    "整箱重量 max": null,
    "Payment term": null,
    "交貨條件": null,
    "Packing info": null,
    "付款條件": null,
    "Q'ty Allowance%": null,
    "包裝資訊": null,
    "Reports": null,
    "允收量%": null,
    "索取報告": null,
    "舊系統備註": "出貨文件 - 請參閱出貨文件檔"
  },
  {
    "客戶編號": "U003",
    "使用集團設定": null,
    "集團包裝要求(代入)": null,
    "訂單包裝要求(顯示)": null,
    "客戶簡稱": "UNBRAKO",
    "報告email": null,
    "客戶包裝要求": null,
    "客戶集團代號": null,
    "負責業務": null,
    "分部位置": null,
    "幣別": null,
    "客戶全名": "UNBRAKO PRODUCTS (S) PTE. LTD.",
    "匯率": null,
    "客戶地址": "627 ALJUNIED ROAD\n#05-00 PACIFIC BUIDLING\nSINAPORE 389837",
    "付款日期": null,
    "客戶電話": "65-292-2787\/298-7052",
    "發票地址": null,
    "客戶傳真": "65-298-2893",
    "invoice Email": null,
    "供應商電話": null,
    "供應商傳真": null,
    "客人負責人": null,
    "客人聯絡人": null,
    "供應商聯絡人": null,
    "客人採購": null,
    "客人業務": null,
    "負責船務": null,
    "標籤": null,
    "棧板格式": null,
    "出歐洲 CBAMnote": null,
    "SC shipping  mark": null,
    "紙箱格式": null,
    "Ship to add.": null,
    "整箱重量 max": null,
    "Payment term": null,
    "交貨條件": null,
    "Packing info": null,
    "付款條件": null,
    "Q'ty Allowance%": null,
    "包裝資訊": null,
    "Reports": null,
    "允收量%": null,
    "索取報告": null,
    "舊系統備註": "\n1. 出貨文件: 請參閱出貨文件檔"
  },
  {
    "客戶編號": "U002",
    "使用集團設定": null,
    "集團包裝要求(代入)": null,
    "訂單包裝要求(顯示)": null,
    "客戶簡稱": "UNITED",
    "報告email": null,
    "客戶包裝要求": null,
    "客戶集團代號": null,
    "負責業務": null,
    "分部位置": null,
    "幣別": null,
    "客戶全名": "UNITED AUTOMOTIVE AGENCIES",
    "匯率": null,
    "客戶地址": "OWEN ROAD P.O. BOX 71\nSINGAPORE 9121\nSINGAPORE",
    "付款日期": null,
    "客戶電話": "65-292-8925",
    "發票地址": null,
    "客戶傳真": "65-299-4835",
    "invoice Email": null,
    "供應商電話": null,
    "供應商傳真": null,
    "客人負責人": null,
    "客人聯絡人": "WILLIAM",
    "供應商聯絡人": null,
    "客人採購": null,
    "客人業務": null,
    "負責船務": null,
    "標籤": null,
    "棧板格式": null,
    "出歐洲 CBAMnote": null,
    "SC shipping  mark": null,
    "紙箱格式": null,
    "Ship to add.": null,
    "整箱重量 max": null,
    "Payment term": null,
    "交貨條件": null,
    "Packing info": null,
    "付款條件": null,
    "Q'ty Allowance%": null,
    "包裝資訊": null,
    "Reports": null,
    "允收量%": null,
    "索取報告": null,
    "舊系統備註": null
  },
  {
    "客戶編號": "U001",
    "使用集團設定": null,
    "集團包裝要求(代入)": null,
    "訂單包裝要求(顯示)": null,
    "客戶簡稱": "U.G.",
    "報告email": null,
    "客戶包裝要求": null,
    "客戶集團代號": null,
    "負責業務": null,
    "分部位置": null,
    "幣別": null,
    "客戶全名": "UGIVIS",
    "匯率": null,
    "客戶地址": "ZAC DE L'OUSSON \n01300 BELLEY\nFRANCE",
    "付款日期": null,
    "客戶電話": "33-79-813-690",
    "發票地址": null,
    "客戶傳真": "33-79-815-310\/810374",
    "invoice Email": null,
    "供應商電話": null,
    "供應商傳真": null,
    "客人負責人": null,
    "客人聯絡人": "JEAN VILLETTE \/ PIERRE BARBIN ",
    "供應商聯絡人": null,
    "客人採購": null,
    "客人業務": null,
    "負責船務": null,
    "標籤": null,
    "棧板格式": null,
    "出歐洲 CBAMnote": null,
    "SC shipping  mark": null,
    "紙箱格式": null,
    "Ship to add.": null,
    "整箱重量 max": null,
    "Payment term": null,
    "交貨條件": null,
    "Packing info": null,
    "付款條件": null,
    "Q'ty Allowance%": null,
    "包裝資訊": null,
    "Reports": null,
    "允收量%": null,
    "索取報告": null,
    "舊系統備註": null
  },
  {
    "客戶編號": "T902",
    "使用集團設定": null,
    "集團包裝要求(代入)": null,
    "訂單包裝要求(顯示)": null,
    "客戶簡稱": "谷信",
    "報告email": null,
    "客戶包裝要求": null,
    "客戶集團代號": null,
    "負責業務": null,
    "分部位置": null,
    "幣別": null,
    "客戶全名": "谷信有限公司(TRUSTY SOURCES CORP.)",
    "匯率": null,
    "客戶地址": "台中市南屯區精科六路7號 (40852)\n\n",
    "付款日期": null,
    "客戶電話": "(04)2358-8568",
    "發票地址": null,
    "客戶傳真": "(04)2358-3583",
    "invoice Email": null,
    "供應商電話": null,
    "供應商傳真": null,
    "客人負責人": "林",
    "客人聯絡人": null,
    "供應商聯絡人": null,
    "客人採購": null,
    "客人業務": null,
    "負責船務": null,
    "標籤": null,
    "棧板格式": null,
    "出歐洲 CBAMnote": null,
    "SC shipping  mark": null,
    "紙箱格式": null,
    "Ship to add.": null,
    "整箱重量 max": null,
    "Payment term": null,
    "交貨條件": null,
    "Packing info": null,
    "付款條件": null,
    "Q'ty Allowance%": null,
    "包裝資訊": null,
    "Reports": null,
    "允收量%": null,
    "索取報告": null,
    "舊系統備註": null
  },
  {
    "客戶編號": "T901",
    "使用集團設定": null,
    "集團包裝要求(代入)": null,
    "訂單包裝要求(顯示)": null,
    "客戶簡稱": "成盈",
    "報告email": null,
    "客戶包裝要求": null,
    "客戶集團代號": null,
    "負責業務": null,
    "分部位置": null,
    "幣別": null,
    "客戶全名": "TSENG WIN TRADING CO.,LTD.",
    "匯率": null,
    "客戶地址": "高雄市左營區博愛三路12號5樓\n\n",
    "付款日期": null,
    "客戶電話": "07 3591472",
    "發票地址": null,
    "客戶傳真": "07 3460055",
    "invoice Email": null,
    "供應商電話": null,
    "供應商傳真": null,
    "客人負責人": null,
    "客人聯絡人": "曾炳棠",
    "供應商聯絡人": null,
    "客人採購": null,
    "客人業務": null,
    "負責船務": null,
    "標籤": null,
    "棧板格式": null,
    "出歐洲 CBAMnote": null,
    "SC shipping  mark": null,
    "紙箱格式": null,
    "Ship to add.": null,
    "整箱重量 max": null,
    "Payment term": null,
    "交貨條件": null,
    "Packing info": null,
    "付款條件": null,
    "Q'ty Allowance%": null,
    "包裝資訊": null,
    "Reports": null,
    "允收量%": null,
    "索取報告": null,
    "舊系統備註": "出貨文件  - 請參閱出貨文件檔"
  },
  {
    "客戶編號": "T045",
    "使用集團設定": null,
    "集團包裝要求(代入)": null,
    "訂單包裝要求(顯示)": null,
    "客戶簡稱": "TR",
    "報告email": null,
    "客戶包裝要求": null,
    "客戶集團代號": null,
    "負責業務": null,
    "分部位置": null,
    "幣別": null,
    "客戶全名": "TR Germany GmbH (T045-GERMANY)",
    "匯率": null,
    "客戶地址": "Lerchenweg 99\n33415 Verl\n",
    "付款日期": null,
    "客戶電話": "5246 50320-24",
    "發票地址": null,
    "客戶傳真": "5246 50320-924",
    "invoice Email": "simoneg@trkuhlmann.com",
    "供應商電話": null,
    "供應商傳真": null,
    "客人負責人": "Simone Georgi",
    "客人聯絡人": null,
    "供應商聯絡人": null,
    "客人採購": null,
    "客人業務": null,
    "負責船務": null,
    "標籤": null,
    "棧板格式": null,
    "出歐洲 CBAMnote": null,
    "SC shipping  mark": null,
    "紙箱格式": null,
    "Ship to add.": null,
    "整箱重量 max": null,
    "Payment term": null,
    "交貨條件": null,
    "Packing info": null,
    "付款條件": null,
    "Q'ty Allowance%": null,
    "包裝資訊": null,
    "Reports": null,
    "允收量%": null,
    "索取報告": null,
    "舊系統備註": "DHL account 968864485\n\n"
  },
  {
    "客戶編號": "T044",
    "使用集團設定": null,
    "集團包裝要求(代入)": null,
    "訂單包裝要求(顯示)": null,
    "客戶簡稱": "Tuhewi",
    "報告email": null,
    "客戶包裝要求": null,
    "客戶集團代號": null,
    "負責業務": null,
    "分部位置": null,
    "幣別": null,
    "客戶全名": "Walter Martínez S.A.U.- Tuhewi",
    "匯率": null,
    "客戶地址": "TECHNICAL& LOGISTICS CENTER:   \nARROYO DEL SOTO 5-7  P.LA LAGUNA \n28914 LEGANÉS (MADRID)       ",
    "付款日期": null,
    "客戶電話": "+34 916426657          ",
    "發票地址": null,
    "客戶傳真": "+34 916114356  ",
    "invoice Email": "comercial-area@tuhewi.com",
    "供應商電話": null,
    "供應商傳真": null,
    "客人負責人": null,
    "客人聯絡人": "Adrian Oropesa Galache",
    "供應商聯絡人": null,
    "客人採購": null,
    "客人業務": null,
    "負責船務": null,
    "標籤": null,
    "棧板格式": null,
    "出歐洲 CBAMnote": null,
    "SC shipping  mark": null,
    "紙箱格式": null,
    "Ship to add.": null,
    "整箱重量 max": null,
    "Payment term": null,
    "交貨條件": null,
    "Packing info": null,
    "付款條件": null,
    "Q'ty Allowance%": null,
    "包裝資訊": null,
    "Reports": null,
    "允收量%": null,
    "索取報告": null,
    "舊系統備註": "FISCAL ADDRESS\nWALTER MARTINEZ SAU\nTURIASO 29 PLA-ZA\n50197 ZARAGOZA (SPAIN)\nCIF. : A50223940            \n\n\nWAREHOUSE ADDRESS\nWALTER MATINEZ (TUHEWI)\nCALLE ARROYO DEL SOTO NAVE 5-7 \nP.I LA LAGUNA 28914 LEGANES (MADRID)\nCIF. : A50223940            \n"
  },
  {
    "客戶編號": "T043",
    "使用集團設定": null,
    "集團包裝要求(代入)": null,
    "訂單包裝要求(顯示)": null,
    "客戶簡稱": "GRS",
    "報告email": null,
    "客戶包裝要求": null,
    "客戶集團代號": null,
    "負責業務": null,
    "分部位置": null,
    "幣別": null,
    "客戶全名": "Grand River Supply",
    "匯率": null,
    "客戶地址": "3075 Baldwin St. Hudsonville, MI 49426\n",
    "付款日期": null,
    "客戶電話": "616 460-9058",
    "發票地址": null,
    "客戶傳真": null,
    "invoice Email": "st@tworiverfasteners.com  ",
    "供應商電話": null,
    "供應商傳真": null,
    "客人負責人": null,
    "客人聯絡人": "sterrill@grsupply.com",
    "供應商聯絡人": "bmol@grsupply.com",
    "客人採購": null,
    "客人業務": null,
    "負責船務": null,
    "標籤": null,
    "棧板格式": null,
    "出歐洲 CBAMnote": null,
    "SC shipping  mark": null,
    "紙箱格式": null,
    "Ship to add.": null,
    "整箱重量 max": null,
    "Payment term": null,
    "交貨條件": null,
    "Packing info": null,
    "付款條件": null,
    "Q'ty Allowance%": null,
    "包裝資訊": null,
    "Reports": null,
    "允收量%": null,
    "索取報告": null,
    "舊系統備註": null
  },
  {
    "客戶編號": "T042",
    "使用集團設定": null,
    "集團包裝要求(代入)": null,
    "訂單包裝要求(顯示)": null,
    "客戶簡稱": "Tornillos ",
    "報告email": null,
    "客戶包裝要求": null,
    "客戶集團代號": null,
    "負責業務": null,
    "分部位置": null,
    "幣別": null,
    "客戶全名": "Tornillos Gutemberto S.A.S.",
    "匯率": null,
    "客戶地址": "Calle 19 sur 28-08 Bogota, Colombia",
    "付款日期": null,
    "客戶電話": "+57 311 5312540",
    "發票地址": null,
    "客戶傳真": null,
    "invoice Email": "administracion@tornillosgutemberto.co",
    "供應商電話": null,
    "供應商傳真": null,
    "客人負責人": null,
    "客人聯絡人": null,
    "供應商聯絡人": null,
    "客人採購": null,
    "客人業務": null,
    "負責船務": null,
    "標籤": null,
    "棧板格式": null,
    "出歐洲 CBAMnote": null,
    "SC shipping  mark": null,
    "紙箱格式": null,
    "Ship to add.": null,
    "整箱重量 max": null,
    "Payment term": null,
    "交貨條件": null,
    "Packing info": null,
    "付款條件": null,
    "Q'ty Allowance%": null,
    "包裝資訊": null,
    "Reports": null,
    "允收量%": null,
    "索取報告": null,
    "舊系統備註": null
  },
  {
    "客戶編號": "T041",
    "使用集團設定": null,
    "集團包裝要求(代入)": null,
    "訂單包裝要求(顯示)": null,
    "客戶簡稱": "TOWER FASTENERS",
    "報告email": null,
    "客戶包裝要求": null,
    "客戶集團代號": null,
    "負責業務": null,
    "分部位置": null,
    "幣別": null,
    "客戶全名": "TOWER FASTENERS",
    "匯率": null,
    "客戶地址": "1690 NORTH OCEAN AVE.\nHOLTSVILLE,NY 11742-1839\nUSA",
    "付款日期": null,
    "客戶電話": "800-688-6937",
    "發票地址": null,
    "客戶傳真": "631-289-3838",
    "invoice Email": "PMacGradyJr@TowerFast.com",
    "供應商電話": null,
    "供應商傳真": null,
    "客人負責人": null,
    "客人聯絡人": "Paul MacGrady Jr",
    "供應商聯絡人": null,
    "客人採購": null,
    "客人業務": null,
    "負責船務": null,
    "標籤": null,
    "棧板格式": null,
    "出歐洲 CBAMnote": null,
    "SC shipping  mark": null,
    "紙箱格式": null,
    "Ship to add.": null,
    "整箱重量 max": null,
    "Payment term": null,
    "交貨條件": null,
    "Packing info": null,
    "付款條件": null,
    "Q'ty Allowance%": null,
    "包裝資訊": null,
    "Reports": null,
    "允收量%": null,
    "索取報告": null,
    "舊系統備註": "Please reach out to Imports@modetransportation.com to schedule pickup.\ngreg.ryan@modetransportation.com \n\naccounting department. For future reference, their email address is Acctspayable@towerfast.com.\n\n"
  },
  {
    "客戶編號": "T040",
    "使用集團設定": null,
    "集團包裝要求(代入)": null,
    "訂單包裝要求(顯示)": null,
    "客戶簡稱": "TR NORWAY",
    "報告email": null,
    "客戶包裝要求": null,
    "客戶集團代號": null,
    "負責業務": null,
    "分部位置": null,
    "幣別": null,
    "客戶全名": "TR Fastenings Norge AS",
    "匯率": null,
    "客戶地址": "Masteveien 8, 1481 Hagan, Norway",
    "付款日期": null,
    "客戶電話": "+47 6706 7000\/+47 6706 7016",
    "發票地址": null,
    "客戶傳真": null,
    "invoice Email": null,
    "供應商電話": null,
    "供應商傳真": null,
    "客人負責人": "NORWAY",
    "客人聯絡人": "Sindre Skiaker",
    "供應商聯絡人": null,
    "客人採購": null,
    "客人業務": null,
    "負責船務": null,
    "標籤": null,
    "棧板格式": null,
    "出歐洲 CBAMnote": null,
    "SC shipping  mark": null,
    "紙箱格式": null,
    "Ship to add.": null,
    "整箱重量 max": null,
    "Payment term": null,
    "交貨條件": null,
    "Packing info": null,
    "付款條件": null,
    "Q'ty Allowance%": null,
    "包裝資訊": null,
    "Reports": null,
    "允收量%": null,
    "索取報告": null,
    "舊系統備註": null
  },
  {
    "客戶編號": "T039",
    "使用集團設定": null,
    "集團包裝要求(代入)": null,
    "訂單包裝要求(顯示)": null,
    "客戶簡稱": "TR",
    "報告email": null,
    "客戶包裝要求": null,
    "客戶集團代號": null,
    "負責業務": null,
    "分部位置": null,
    "幣別": null,
    "客戶全名": "TR FASTENINGS ESPANA",
    "匯率": null,
    "客戶地址": "CALLE DE LA CIENCIA, 43\nVILADECANS 08840 BARCELONA SPAIN\nVAT number ESB66870494",
    "付款日期": null,
    "客戶電話": "0034 936472245",
    "發票地址": null,
    "客戶傳真": null,
    "invoice Email": null,
    "供應商電話": null,
    "供應商傳真": null,
    "客人負責人": "SPAIN",
    "客人聯絡人": null,
    "供應商聯絡人": null,
    "客人採購": null,
    "客人業務": null,
    "負責船務": null,
    "標籤": null,
    "棧板格式": null,
    "出歐洲 CBAMnote": null,
    "SC shipping  mark": null,
    "紙箱格式": null,
    "Ship to add.": null,
    "整箱重量 max": null,
    "Payment term": null,
    "交貨條件": null,
    "Packing info": null,
    "付款條件": null,
    "Q'ty Allowance%": null,
    "包裝資訊": null,
    "Reports": null,
    "允收量%": null,
    "索取報告": null,
    "舊系統備註": " copying the email address 'accounts@trfastenings.es'.when you send your invoices."
  },
  {
    "客戶編號": "T038",
    "使用集團設定": null,
    "集團包裝要求(代入)": null,
    "訂單包裝要求(顯示)": null,
    "客戶簡稱": "TR",
    "報告email": null,
    "客戶包裝要求": null,
    "客戶集團代號": null,
    "負責業務": null,
    "分部位置": null,
    "幣別": null,
    "客戶全名": "TR Formac Co., Ltd.",
    "匯率": null,
    "客戶地址": "28, 3rd Floor, Motorway Road, Prawet, Prawet, Bangkok 10250 Thailand",
    "付款日期": null,
    "客戶電話": "(+66) 2041 3340",
    "發票地址": null,
    "客戶傳真": "(+66) 2041 3340",
    "invoice Email": null,
    "供應商電話": null,
    "供應商傳真": null,
    "客人負責人": "Thailand",
    "客人聯絡人": null,
    "供應商聯絡人": null,
    "客人採購": null,
    "客人業務": null,
    "負責船務": null,
    "標籤": null,
    "棧板格式": null,
    "出歐洲 CBAMnote": null,
    "SC shipping  mark": null,
    "紙箱格式": null,
    "Ship to add.": null,
    "整箱重量 max": null,
    "Payment term": null,
    "交貨條件": null,
    "Packing info": null,
    "付款條件": null,
    "Q'ty Allowance%": null,
    "包裝資訊": null,
    "Reports": null,
    "允收量%": null,
    "索取報告": null,
    "舊系統備註": null
  },
  {
    "客戶編號": "T037",
    "使用集團設定": null,
    "集團包裝要求(代入)": null,
    "訂單包裝要求(顯示)": null,
    "客戶簡稱": "TR Hungary",
    "報告email": null,
    "客戶包裝要求": null,
    "客戶集團代號": null,
    "負責業務": null,
    "分部位置": null,
    "幣別": null,
    "客戶全名": "TR Hungary KFT",
    "匯率": null,
    "客戶地址": "2310 Szigetszentmiklós, Diósgyőri utca 2.\n\n",
    "付款日期": null,
    "客戶電話": "0036 24530622",
    "發票地址": null,
    "客戶傳真": "0036 24516961",
    "invoice Email": "susanm@trfastenings.com",
    "供應商電話": null,
    "供應商傳真": null,
    "客人負責人": "HUNGARY",
    "客人聯絡人": "Susan McMichael",
    "供應商聯絡人": null,
    "客人採購": null,
    "客人業務": null,
    "負責船務": null,
    "標籤": null,
    "棧板格式": null,
    "出歐洲 CBAMnote": null,
    "SC shipping  mark": null,
    "紙箱格式": null,
    "Ship to add.": null,
    "整箱重量 max": null,
    "Payment term": null,
    "交貨條件": null,
    "Packing info": null,
    "付款條件": null,
    "Q'ty Allowance%": null,
    "包裝資訊": null,
    "Reports": null,
    "允收量%": null,
    "索取報告": null,
    "舊系統備註": "TNT Economy, our account 23606.\nDHL on our account number 962949221 改成 954 515 355\n\nDHL SEA – freight contact Raiko Chen email Raiko.chen@dhl.com , Tel 00886 266038000 , 3F No 189 Sec 2 Jiuzong Rd , Neihu District , Taipei City , 11494 Taiwan.\n\nALL SHIPMENTS BELOW 40KGS PLEASE DESPATCH VIA TNT ECONOMY EXPRESS QUOTING ACCOUNT NO #23606. \nABOVE 40KGS DESPATCH VIA DHL SEA FREIGHT\n\nPlease find contact names in TR Hungary for shipping and payment\nFor shipping please contact:\nNikolett Laczkone , Purchasing expeditor\nTR Hungary Kft.\n2310 Szigetszentmiklós\nLeshegy u. 8.\nTel.: 0036 24 525-576\nE-mail: nikolettl@trfastenings.com\n\n\nFor payment please contact:\nBarbara Bratkovics , Finance Assistant\nTR Hungary Kft. \n2310 Szigetszentmiklós, Leshegy 8.\nHungary\nTelefon:    +3624\/539211\n Fax:         +3624\/516961\nemail:       barbarab@trfastenings.com  \n"
  },
  {
    "客戶編號": "T036",
    "使用集團設定": null,
    "集團包裝要求(代入)": null,
    "訂單包裝要求(顯示)": null,
    "客戶簡稱": "TR ",
    "報告email": null,
    "客戶包裝要求": null,
    "客戶集團代號": null,
    "負責業務": null,
    "分部位置": null,
    "幣別": null,
    "客戶全名": "TR SHANGHAI PTE LTD.",
    "匯率": null,
    "客戶地址": "3RD FLOOR, BUILDING 2, NO.399 NORTH FUTE ROAD, WAIGAOQIAO FREE TRADE ZONE PUDONG, SHANGHAI, CHINA, 200131",
    "付款日期": null,
    "客戶電話": "(86)021-50326557",
    "發票地址": null,
    "客戶傳真": "(86)021-50325775",
    "invoice Email": "brook.xi@trformac.com.cn ",
    "供應商電話": null,
    "供應商傳真": null,
    "客人負責人": "SHANGHAI",
    "客人聯絡人": "brook.xi",
    "供應商聯絡人": null,
    "客人採購": null,
    "客人業務": null,
    "負責船務": null,
    "標籤": null,
    "棧板格式": null,
    "出歐洲 CBAMnote": null,
    "SC shipping  mark": null,
    "紙箱格式": null,
    "Ship to add.": null,
    "整箱重量 max": null,
    "Payment term": null,
    "交貨條件": null,
    "Packing info": null,
    "付款條件": null,
    "Q'ty Allowance%": null,
    "包裝資訊": null,
    "Reports": null,
    "允收量%": null,
    "索取報告": null,
    "舊系統備註": "pls send to below address:\nTR Formac (ShangHai) Pte Ltd.\nFloor 3,No.1222 Jinhu Rd,Pudong,Shanghai,China\n<tel:(86)021-50326557> Tel:(86)021-50326557\n\nTR Shanghai's TNT account:74711.\nFedex Intl.Priority,our account is 912938549 (這是TNT)\n\nFedex Intl.Priority,our account is 261732238\n\n\n--\nFrom: danping.huang@trformac.com.cn <danping.huang@trformac.com.cn> \nSent: Wednesday, January 22, 2025 3:50 PM\nTo: huangdanping <danping.huang@trformac.com.cn>\nSubject: TR Shanghai Pte Ltd\n\nDear All, \n\nWe appreciate your trust and support in our company all along! Effective from Jan 10th 2025 , our company name will be changed from TR Formac (Shanghai) Pte Ltd to TR Shanghai Pte Ltd. There will be no changes to our address, contact numbers, or any other contact details. All agreements, contracts, and legal obligations will remain valid and in effect.All vendors please be noticed please use TR  Shanghai  Pte Ltd as our head of the official documents especially Invoice.\n\nThanks & Best Regards\nHuangDanping\n---------------------------------------\nTR Formac (ShangHai) Pte Ltd. \nTel：021-50325696-6297\nFax：021-50325775 \nE-mail:danping.huang@trformac.com.cn\n上海市浦东新区合庆镇东胜路38号新发创运工业园区A9幢\n\n\n\n"
  },
  {
    "客戶編號": "T035",
    "使用集團設定": null,
    "集團包裝要求(代入)": null,
    "訂單包裝要求(顯示)": null,
    "客戶簡稱": "TR",
    "報告email": null,
    "客戶包裝要求": null,
    "客戶集團代號": null,
    "負責業務": null,
    "分部位置": null,
    "幣別": null,
    "客戶全名": "TR FASTENING LTD",
    "匯率": null,
    "客戶地址": "Ikon Trading Estate, Droitwich Road, Hartlebury,Worcester \nDY10 4EU ",
    "付款日期": null,
    "客戶電話": null,
    "發票地址": null,
    "客戶傳真": "0870 4587849",
    "invoice Email": null,
    "供應商電話": null,
    "供應商傳真": null,
    "客人負責人": "UK",
    "客人聯絡人": null,
    "供應商聯絡人": null,
    "客人採購": null,
    "客人業務": null,
    "負責船務": null,
    "標籤": null,
    "棧板格式": null,
    "出歐洲 CBAMnote": null,
    "SC shipping  mark": null,
    "紙箱格式": null,
    "Ship to add.": null,
    "整箱重量 max": null,
    "Payment term": null,
    "交貨條件": null,
    "Packing info": null,
    "付款條件": null,
    "Q'ty Allowance%": null,
    "包裝資訊": null,
    "Reports": null,
    "允收量%": null,
    "索取報告": null,
    "舊系統備註": "New delivery address for TR 67 orders  below:\nTR FASTENINGS WATERSIDE PARK    \nUNIT C                          \nGOLDSHILL WAY                   \nTIPTON                          \nDY4 OPU                         \nPhone: 0121 5212051     Fax :   \nEmail:ashleye@trfastenings.com  \n\nInvoice address:\nTrifast House, Bellbrook Park, Uckfield, East Sussex, TN22 1QW U.K.\n\ndocument to:\nMrs Julie Coupland\nTR Fastenings Limited\nBell Lane Industrial Estate\nUckfield\nEast Sussex\nTN22 1QW\n\nTel: 0044 1825 7472414\n\n"
  },
  {
    "客戶編號": "T034",
    "使用集團設定": null,
    "集團包裝要求(代入)": null,
    "訂單包裝要求(顯示)": null,
    "客戶簡稱": "Thomas",
    "報告email": null,
    "客戶包裝要求": null,
    "客戶集團代號": null,
    "負責業務": null,
    "分部位置": null,
    "幣別": null,
    "客戶全名": "Thomas Warburton Pty. Ltd",
    "匯率": null,
    "客戶地址": "16-26 Dunlop Road \nP.O. Box 566 \nMulgrave, Victoria 3170 \nAUSTRALIA",
    "付款日期": null,
    "客戶電話": "+61 395 743 400",
    "發票地址": null,
    "客戶傳真": "+61 395 743 481",
    "invoice Email": "Tom.Eertman@wuerth-industrie.com",
    "供應商電話": null,
    "供應商傳真": null,
    "客人負責人": null,
    "客人聯絡人": "Tom",
    "供應商聯絡人": null,
    "客人採購": null,
    "客人業務": null,
    "負責船務": null,
    "標籤": null,
    "棧板格式": null,
    "出歐洲 CBAMnote": null,
    "SC shipping  mark": null,
    "紙箱格式": null,
    "Ship to add.": null,
    "整箱重量 max": null,
    "Payment term": null,
    "交貨條件": null,
    "Packing info": null,
    "付款條件": null,
    "Q'ty Allowance%": null,
    "包裝資訊": null,
    "Reports": null,
    "允收量%": null,
    "索取報告": null,
    "舊系統備註": null
  },
  {
    "客戶編號": "T033",
    "使用集團設定": null,
    "集團包裝要求(代入)": null,
    "訂單包裝要求(顯示)": null,
    "客戶簡稱": "TR",
    "報告email": null,
    "客戶包裝要求": null,
    "客戶集團代號": null,
    "負責業務": null,
    "分部位置": null,
    "幣別": null,
    "客戶全名": "TR FASTENINGS LTD",
    "匯率": null,
    "客戶地址": "The Thistle Building 9 Cairn Court\nEast Kilbride Scotland G74 4NB\n",
    "付款日期": null,
    "客戶電話": "01698 717000",
    "發票地址": null,
    "客戶傳真": "0870 4587874",
    "invoice Email": "jasonb@trfastenings.com",
    "供應商電話": null,
    "供應商傳真": null,
    "客人負責人": "SCOTLAND",
    "客人聯絡人": "JASON",
    "供應商聯絡人": null,
    "客人採購": null,
    "客人業務": null,
    "負責船務": null,
    "標籤": null,
    "棧板格式": null,
    "出歐洲 CBAMnote": null,
    "SC shipping  mark": null,
    "紙箱格式": null,
    "Ship to add.": null,
    "整箱重量 max": null,
    "Payment term": null,
    "交貨條件": null,
    "Packing info": null,
    "付款條件": null,
    "Q'ty Allowance%": null,
    "包裝資訊": null,
    "Reports": null,
    "允收量%": null,
    "索取報告": null,
    "舊系統備註": "dhl on our account number 960069268"
  },
  {
    "客戶編號": "T032",
    "使用集團設定": null,
    "集團包裝要求(代入)": null,
    "訂單包裝要求(顯示)": null,
    "客戶簡稱": "TR",
    "報告email": null,
    "客戶包裝要求": null,
    "客戶集團代號": null,
    "負責業務": null,
    "分部位置": null,
    "幣別": null,
    "客戶全名": "TR FASTENINGS INC.",
    "匯率": null,
    "客戶地址": "10811 Vinecrest Drive Suite 190 Houston Texas 77086\n\n",
    "付款日期": null,
    "客戶電話": "800 280 2181",
    "發票地址": null,
    "客戶傳真": "281 807 0620",
    "invoice Email": "james.bohannon@trfastenings.us",
    "供應商電話": null,
    "供應商傳真": null,
    "客人負責人": "USA",
    "客人聯絡人": "JAMES",
    "供應商聯絡人": null,
    "客人採購": null,
    "客人業務": null,
    "負責船務": null,
    "標籤": null,
    "棧板格式": null,
    "出歐洲 CBAMnote": null,
    "SC shipping  mark": null,
    "紙箱格式": null,
    "Ship to add.": null,
    "整箱重量 max": null,
    "Payment term": null,
    "交貨條件": null,
    "Packing info": null,
    "付款條件": null,
    "Q'ty Allowance%": null,
    "包裝資訊": null,
    "Reports": null,
    "允收量%": null,
    "索取報告": null,
    "舊系統備註": "FEDEX NO.432676455   (ECONOMY)\nDHL on acct # 962153286\n\nFeel free to ship the below on the sea.\nUntil further notice, for sea shipments, please select a freight forwarder from the following list.\n1.AIT\n2.Rim Logistics\n3.Scanwell\n4.Bollore\n\nPlease start with #1 AIT and if they don’t have space to move the freight, please feel free to reach out to #2 Rim and so on.\nThe idea is to move the parts via sea as fast as possible with who ever has room first.\nYou do not have to ask TR which sea freight forwarder to use, but our preference is AIT if they have room.\nHope this makes sense and if any questions please feel free to ask.\n\n"
  },
  {
    "客戶編號": "T031",
    "使用集團設定": null,
    "集團包裝要求(代入)": null,
    "訂單包裝要求(顯示)": null,
    "客戶簡稱": "TR",
    "報告email": null,
    "客戶包裝要求": null,
    "客戶集團代號": null,
    "負責業務": null,
    "分部位置": null,
    "幣別": null,
    "客戶全名": "TR FORMAC PTE LTD",
    "匯率": null,
    "客戶地址": "57 Senoko Road Singapore 758121\n\n",
    "付款日期": null,
    "客戶電話": "(65)6759 6033",
    "發票地址": null,
    "客戶傳真": "(65)6759 6022",
    "invoice Email": null,
    "供應商電話": null,
    "供應商傳真": null,
    "客人負責人": "Singapore",
    "客人聯絡人": null,
    "供應商聯絡人": null,
    "客人採購": null,
    "客人業務": null,
    "負責船務": null,
    "標籤": null,
    "棧板格式": null,
    "出歐洲 CBAMnote": null,
    "SC shipping  mark": null,
    "紙箱格式": null,
    "Ship to add.": null,
    "整箱重量 max": null,
    "Payment term": null,
    "交貨條件": null,
    "Packing info": null,
    "付款條件": null,
    "Q'ty Allowance%": null,
    "包裝資訊": null,
    "Reports": null,
    "允收量%": null,
    "索取報告": null,
    "舊系統備註": "FedEx account number is # 1886-0429-3\nOur UPS account number is # 41X92E\n\n"
  },
  {
    "客戶編號": "T030",
    "使用集團設定": null,
    "集團包裝要求(代入)": null,
    "訂單包裝要求(顯示)": null,
    "客戶簡稱": "TR",
    "報告email": null,
    "客戶包裝要求": null,
    "客戶集團代號": null,
    "負責業務": null,
    "分部位置": null,
    "幣別": null,
    "客戶全名": "TR HOLLAND",
    "匯率": null,
    "客戶地址": "KELVINSTRAAT 5 7575 AS OLDENZAAL\nTHE NETHERLANDS\n",
    "付款日期": null,
    "客戶電話": "31 541 511515",
    "發票地址": null,
    "客戶傳真": "31 541 517134",
    "invoice Email": "wouton@trfastenings.com",
    "供應商電話": null,
    "供應商傳真": null,
    "客人負責人": "NETHERLANDS",
    "客人聯絡人": null,
    "供應商聯絡人": null,
    "客人採購": null,
    "客人業務": null,
    "負責船務": null,
    "標籤": null,
    "棧板格式": null,
    "出歐洲 CBAMnote": null,
    "SC shipping  mark": null,
    "紙箱格式": null,
    "Ship to add.": null,
    "整箱重量 max": null,
    "Payment term": null,
    "交貨條件": null,
    "Packing info": null,
    "付款條件": null,
    "Q'ty Allowance%": null,
    "包裝資訊": null,
    "Reports": null,
    "允收量%": null,
    "索取報告": null,
    "舊系統備註": "TNT on our account 42661\nFedex International Priority on our account 2801-2252-1.\nYou can ship by DHL, account 961919490\n\nDetails forwarder:Taiwan sea \nContact Sandy Tseng \nCompany T.H.I. GROUP Ltd. Taipei Office \nPhone +886-2-27532093 #173 \nFax  +886-2-27603679 \/ 27653522 \nEmail   sandytseng@thi-group.com\n \n"
  },
  {
    "客戶編號": "T029",
    "使用集團設定": null,
    "集團包裝要求(代入)": null,
    "訂單包裝要求(顯示)": null,
    "客戶簡稱": "TR",
    "報告email": null,
    "客戶包裝要求": null,
    "客戶集團代號": null,
    "負責業務": null,
    "分部位置": null,
    "幣別": null,
    "客戶全名": "TR FASTENINGS LTD (T029-DURHAM-UK)",
    "匯率": null,
    "客戶地址": "Angels Close Aycliffe Industrial Estate\nNewton Aycliffe Co Durham DL5 6BG UK\n",
    "付款日期": null,
    "客戶電話": "01698 717 018",
    "發票地址": null,
    "客戶傳真": "0870 458 7869",
    "invoice Email": "susanm@trfastenings.com",
    "供應商電話": null,
    "供應商傳真": null,
    "客人負責人": "UK",
    "客人聯絡人": null,
    "供應商聯絡人": null,
    "客人採購": null,
    "客人業務": null,
    "負責船務": null,
    "標籤": null,
    "棧板格式": null,
    "出歐洲 CBAMnote": null,
    "SC shipping  mark": null,
    "紙箱格式": null,
    "Ship to add.": null,
    "整箱重量 max": null,
    "Payment term": null,
    "交貨條件": null,
    "Packing info": null,
    "付款條件": null,
    "Q'ty Allowance%": null,
    "包裝資訊": null,
    "Reports": null,
    "允收量%": null,
    "索取報告": null,
    "舊系統備註": "SHIP VIA TR DHL:960069268\n\nTNT using the TR account number 1002759\n"
  },
  {
    "客戶編號": "T028",
    "使用集團設定": null,
    "集團包裝要求(代入)": null,
    "訂單包裝要求(顯示)": null,
    "客戶簡稱": "TR",
    "報告email": null,
    "客戶包裝要求": null,
    "客戶集團代號": null,
    "負責業務": null,
    "分部位置": null,
    "幣別": null,
    "客戶全名": "TR FASTENINGS LTD (T028-TIPTON-U.K)",
    "匯率": null,
    "客戶地址": "WATERSIDE PARK, GOLDS HILLS WAY, TIPTON\nDY4 0WP UK\n",
    "付款日期": null,
    "客戶電話": "0121 521 0133",
    "發票地址": null,
    "客戶傳真": "0870 458 7920",
    "invoice Email": null,
    "供應商電話": null,
    "供應商傳真": null,
    "客人負責人": "UK",
    "客人聯絡人": null,
    "供應商聯絡人": null,
    "客人採購": null,
    "客人業務": null,
    "負責船務": null,
    "標籤": null,
    "棧板格式": null,
    "出歐洲 CBAMnote": null,
    "SC shipping  mark": null,
    "紙箱格式": null,
    "Ship to add.": null,
    "整箱重量 max": null,
    "Payment term": null,
    "交貨條件": null,
    "Packing info": null,
    "付款條件": null,
    "Q'ty Allowance%": null,
    "包裝資訊": null,
    "Reports": null,
    "允收量%": null,
    "索取報告": null,
    "舊系統備註": "DHL A\/C:960069268\nTNT using the TR account number 1002759"
  },
  {
    "客戶編號": "T027",
    "使用集團設定": null,
    "集團包裝要求(代入)": null,
    "訂單包裝要求(顯示)": null,
    "客戶簡稱": "TECNOFUN",
    "報告email": null,
    "客戶包裝要求": null,
    "客戶集團代號": null,
    "負責業務": null,
    "分部位置": null,
    "幣別": null,
    "客戶全名": "TECNOFUNDICIONES Y TORNILLOS DEL VALLE",
    "匯率": null,
    "客戶地址": "CALLE 10 #35-252,ACOPI,YUMBO,VALLE DEL CAUCA\nCOLOMBIA,S.A.\n",
    "付款日期": null,
    "客戶電話": "2-6643414",
    "發票地址": null,
    "客戶傳真": null,
    "invoice Email": null,
    "供應商電話": null,
    "供應商傳真": null,
    "客人負責人": null,
    "客人聯絡人": "LUIS",
    "供應商聯絡人": null,
    "客人採購": null,
    "客人業務": null,
    "負責船務": null,
    "標籤": null,
    "棧板格式": null,
    "出歐洲 CBAMnote": null,
    "SC shipping  mark": null,
    "紙箱格式": null,
    "Ship to add.": null,
    "整箱重量 max": null,
    "Payment term": null,
    "交貨條件": null,
    "Packing info": null,
    "付款條件": null,
    "Q'ty Allowance%": null,
    "包裝資訊": null,
    "Reports": null,
    "允收量%": null,
    "索取報告": null,
    "舊系統備註": null
  },
  {
    "客戶編號": "T026",
    "使用集團設定": null,
    "集團包裝要求(代入)": null,
    "訂單包裝要求(顯示)": null,
    "客戶簡稱": "Tyco",
    "報告email": null,
    "客戶包裝要求": null,
    "客戶集團代號": null,
    "負責業務": null,
    "分部位置": null,
    "幣別": null,
    "客戶全名": "Tyco Safety Products(Shenyang)Co. Ltd",
    "匯率": null,
    "客戶地址": "No.33 Century Road, Hunnan New Zone\nShenyang,Liaoning,China 110179\n",
    "付款日期": null,
    "客戶電話": "0086 24 83780100",
    "發票地址": null,
    "客戶傳真": "0086 24 83780103",
    "invoice Email": "river.eagle@msa.hinet.net",
    "供應商電話": null,
    "供應商傳真": null,
    "客人負責人": "陳子庭",
    "客人聯絡人": null,
    "供應商聯絡人": null,
    "客人採購": null,
    "客人業務": null,
    "負責船務": null,
    "標籤": null,
    "棧板格式": null,
    "出歐洲 CBAMnote": null,
    "SC shipping  mark": null,
    "紙箱格式": null,
    "Ship to add.": null,
    "整箱重量 max": null,
    "Payment term": null,
    "交貨條件": null,
    "Packing info": null,
    "付款條件": null,
    "Q'ty Allowance%": null,
    "包裝資訊": null,
    "Reports": null,
    "允收量%": null,
    "索取報告": null,
    "舊系統備註": "JENNIFER  86-21-61633377 ext 1158,  mobile is 86-15800677771\nPaul Wang  Cell: +139 0297 1020"
  },
  {
    "客戶編號": "T025",
    "使用集團設定": null,
    "集團包裝要求(代入)": null,
    "訂單包裝要求(顯示)": null,
    "客戶簡稱": "TRENDWAR",
    "報告email": null,
    "客戶包裝要求": null,
    "客戶集團代號": null,
    "負責業務": null,
    "分部位置": null,
    "幣別": null,
    "客戶全名": "TRENDWARE\/GOLDBERG",
    "匯率": null,
    "客戶地址": "16 PROCTOR STREET SALEM,MA 01970 USA\n\n",
    "付款日期": null,
    "客戶電話": null,
    "發票地址": null,
    "客戶傳真": null,
    "invoice Email": null,
    "供應商電話": null,
    "供應商傳真": null,
    "客人負責人": null,
    "客人聯絡人": null,
    "供應商聯絡人": null,
    "客人採購": null,
    "客人業務": null,
    "負責船務": null,
    "標籤": null,
    "棧板格式": null,
    "出歐洲 CBAMnote": null,
    "SC shipping  mark": null,
    "紙箱格式": null,
    "Ship to add.": null,
    "整箱重量 max": null,
    "Payment term": null,
    "交貨條件": null,
    "Packing info": null,
    "付款條件": null,
    "Q'ty Allowance%": null,
    "包裝資訊": null,
    "Reports": null,
    "允收量%": null,
    "索取報告": null,
    "舊系統備註": "ECONOMY   FED EX ACCOUNT # 1409-2459-8.\n"
  },
  {
    "客戶編號": "T024",
    "使用集團設定": null,
    "集團包裝要求(代入)": null,
    "訂單包裝要求(顯示)": null,
    "客戶簡稱": "TEKNOLOJ",
    "報告email": null,
    "客戶包裝要求": null,
    "客戶集團代號": null,
    "負責業務": null,
    "分部位置": null,
    "幣別": null,
    "客戶全名": "TEKNOLOJI PERCIN VE MAKINA LTD.",
    "匯率": null,
    "客戶地址": "TEM YOLU ISTOC 3.ADA NO:57 BAGCILAR,\n34217-ISTANBUL-TURKEY\n",
    "付款日期": null,
    "客戶電話": "90 212 659 57 45",
    "發票地址": null,
    "客戶傳真": "90 212 659 57 48",
    "invoice Email": null,
    "供應商電話": null,
    "供應商傳真": null,
    "客人負責人": "SEDAT DENIZ",
    "客人聯絡人": null,
    "供應商聯絡人": null,
    "客人採購": null,
    "客人業務": null,
    "負責船務": null,
    "標籤": null,
    "棧板格式": null,
    "出歐洲 CBAMnote": null,
    "SC shipping  mark": null,
    "紙箱格式": null,
    "Ship to add.": null,
    "整箱重量 max": null,
    "Payment term": null,
    "交貨條件": null,
    "Packing info": null,
    "付款條件": null,
    "Q'ty Allowance%": null,
    "包裝資訊": null,
    "Reports": null,
    "允收量%": null,
    "索取報告": null,
    "舊系統備註": "VAT:8360358939"
  },
  {
    "客戶編號": "T023",
    "使用集團設定": null,
    "集團包裝要求(代入)": null,
    "訂單包裝要求(顯示)": null,
    "客戶簡稱": "TR",
    "報告email": null,
    "客戶包裝要求": null,
    "客戶集團代號": null,
    "負責業務": null,
    "分部位置": null,
    "幣別": null,
    "客戶全名": "TR FASTENINGS AB (T023-SWEDEN)",
    "匯率": null,
    "客戶地址": "Smedjegatan 6, 7tr 131 54 Nacka\nSweden\nEORI number is SE5563009769\n\n",
    "付款日期": null,
    "客戶電話": "08 578 449 00",
    "發票地址": null,
    "客戶傳真": "08 578 449 50",
    "invoice Email": "info@trfastenings.se",
    "供應商電話": null,
    "供應商傳真": null,
    "客人負責人": "HANS KRIISA-Sweden",
    "客人聯絡人": null,
    "供應商聯絡人": null,
    "客人採購": null,
    "客人業務": null,
    "負責船務": null,
    "標籤": null,
    "棧板格式": null,
    "出歐洲 CBAMnote": null,
    "SC shipping  mark": null,
    "紙箱格式": null,
    "Ship to add.": null,
    "整箱重量 max": null,
    "Payment term": null,
    "交貨條件": null,
    "Packing info": null,
    "付款條件": null,
    "Q'ty Allowance%": null,
    "包裝資訊": null,
    "Reports": null,
    "允收量%": null,
    "索取報告": null,
    "舊系統備註": "TNT ACCOUNT NUMBER:51058\nDHL account number:959 169 818\n\nJason Kuo\nAsian Supplier Quality Manager\nTR Fastenings Ltd\nT: +886 926 022033\n"
  },
  {
    "客戶編號": "T022",
    "使用集團設定": null,
    "集團包裝要求(代入)": null,
    "訂單包裝要求(顯示)": null,
    "客戶簡稱": "TECH-NET",
    "報告email": null,
    "客戶包裝要求": null,
    "客戶集團代號": null,
    "負責業務": null,
    "分部位置": null,
    "幣別": null,
    "客戶全名": "TECH-NET GMBH",
    "匯率": null,
    "客戶地址": "CORUNNASTRASSE 1\n58636 ISERLOHN GERMANY\n",
    "付款日期": null,
    "客戶電話": "002 49 2371 152316",
    "發票地址": null,
    "客戶傳真": "002 49 2371 154512",
    "invoice Email": null,
    "供應商電話": null,
    "供應商傳真": null,
    "客人負責人": null,
    "客人聯絡人": null,
    "供應商聯絡人": null,
    "客人採購": null,
    "客人業務": null,
    "負責船務": null,
    "標籤": null,
    "棧板格式": null,
    "出歐洲 CBAMnote": null,
    "SC shipping  mark": null,
    "紙箱格式": null,
    "Ship to add.": null,
    "整箱重量 max": null,
    "Payment term": null,
    "交貨條件": null,
    "Packing info": null,
    "付款條件": null,
    "Q'ty Allowance%": null,
    "包裝資訊": null,
    "Reports": null,
    "允收量%": null,
    "索取報告": null,
    "舊系統備註": null
  },
  {
    "客戶編號": "T021",
    "使用集團設定": null,
    "集團包裝要求(代入)": null,
    "訂單包裝要求(顯示)": null,
    "客戶簡稱": "TRANSACC",
    "報告email": null,
    "客戶包裝要求": null,
    "客戶集團代號": null,
    "負責業務": null,
    "分部位置": null,
    "幣別": null,
    "客戶全名": "TRANSACCIONES FERRETERAS DE COSTA RICA S.A.",
    "匯率": null,
    "客戶地址": "\n\n",
    "付款日期": null,
    "客戶電話": null,
    "發票地址": null,
    "客戶傳真": null,
    "invoice Email": null,
    "供應商電話": null,
    "供應商傳真": null,
    "客人負責人": null,
    "客人聯絡人": null,
    "供應商聯絡人": null,
    "客人採購": null,
    "客人業務": null,
    "負責船務": null,
    "標籤": null,
    "棧板格式": null,
    "出歐洲 CBAMnote": null,
    "SC shipping  mark": null,
    "紙箱格式": null,
    "Ship to add.": null,
    "整箱重量 max": null,
    "Payment term": null,
    "交貨條件": null,
    "Packing info": null,
    "付款條件": null,
    "Q'ty Allowance%": null,
    "包裝資訊": null,
    "Reports": null,
    "允收量%": null,
    "索取報告": null,
    "舊系統備註": "JOSE CUSTOMER"
  },
  {
    "客戶編號": "T020",
    "使用集團設定": null,
    "集團包裝要求(代入)": null,
    "訂單包裝要求(顯示)": null,
    "客戶簡稱": "TECHNO",
    "報告email": null,
    "客戶包裝要求": null,
    "客戶集團代號": null,
    "負責業務": null,
    "分部位置": null,
    "幣別": null,
    "客戶全名": "MR. GHASEM IMAIN DOVECH",
    "匯率": null,
    "客戶地址": "Techno Steel No.17 Omid Passage,Chazvin St.,TEHRAN\nIRAN\n",
    "付款日期": null,
    "客戶電話": "002-98-21-55408383",
    "發票地址": null,
    "客戶傳真": "002-98-21-55405167",
    "invoice Email": "technosteel@locksure.com.tw",
    "供應商電話": null,
    "供應商傳真": null,
    "客人負責人": "TIMOTHY IRWIN",
    "客人聯絡人": null,
    "供應商聯絡人": null,
    "客人採購": null,
    "客人業務": null,
    "負責船務": null,
    "標籤": null,
    "棧板格式": null,
    "出歐洲 CBAMnote": null,
    "SC shipping  mark": null,
    "紙箱格式": null,
    "Ship to add.": null,
    "整箱重量 max": null,
    "Payment term": null,
    "交貨條件": null,
    "Packing info": null,
    "付款條件": null,
    "Q'ty Allowance%": null,
    "包裝資訊": null,
    "Reports": null,
    "允收量%": null,
    "索取報告": null,
    "舊系統備註": "TEL:                    FAX:+98-21-5413507 \n+ 98-21-5410577               +98-21-5405167 \n+98-21-5410753\n+98-21-5410211\n+98-21-5408383\n+98-21-5407979\n\n出貨文件  - 請參閱出貨文件檔\n\n94年出貨走 七洋海運  07-5363757  許's   email:seven01@ms38.hinet.net\n但要國外有電報回來才可走\n要黑名單,c\/o\n\n"
  },
  {
    "客戶編號": "T019",
    "使用集團設定": null,
    "集團包裝要求(代入)": null,
    "訂單包裝要求(顯示)": null,
    "客戶簡稱": "TECHNOMA",
    "報告email": null,
    "客戶包裝要求": null,
    "客戶集團代號": null,
    "負責業務": null,
    "分部位置": null,
    "幣別": null,
    "客戶全名": "TECHNOMAR & ADREM LTD.",
    "匯率": null,
    "客戶地址": "MOTUSE 3, 10619 TALLINN\nESTONIA\n",
    "付款日期": null,
    "客戶電話": "002-372-6564 246",
    "發票地址": null,
    "客戶傳真": "002-372-6564 245",
    "invoice Email": null,
    "供應商電話": null,
    "供應商傳真": null,
    "客人負責人": null,
    "客人聯絡人": "MR. ANDREI",
    "供應商聯絡人": null,
    "客人採購": null,
    "客人業務": null,
    "負責船務": null,
    "標籤": null,
    "棧板格式": null,
    "出歐洲 CBAMnote": null,
    "SC shipping  mark": null,
    "紙箱格式": null,
    "Ship to add.": null,
    "整箱重量 max": null,
    "Payment term": null,
    "交貨條件": null,
    "Packing info": null,
    "付款條件": null,
    "Q'ty Allowance%": null,
    "包裝資訊": null,
    "Reports": null,
    "允收量%": null,
    "索取報告": null,
    "舊系統備註": null
  },
  {
    "客戶編號": "T018",
    "使用集團設定": null,
    "集團包裝要求(代入)": null,
    "訂單包裝要求(顯示)": null,
    "客戶簡稱": "TFP",
    "報告email": null,
    "客戶包裝要求": null,
    "客戶集團代號": null,
    "負責業務": null,
    "分部位置": null,
    "幣別": null,
    "客戶全名": "TRU-FIT CORP",
    "匯率": null,
    "客戶地址": "16-26 Dunlop Road \nP.O. Box 566 \nMulgrave, Victoria 3170 \nAUSTRALIA",
    "付款日期": null,
    "客戶電話": "+61 395 743 400",
    "發票地址": null,
    "客戶傳真": "+61 395 743 481",
    "invoice Email": "Tom.Eertman@wuerth-industrie.com",
    "供應商電話": null

```txt file="customer_schema-0FxPtldtPqdrWJntRDTrFdDZSncy1J.txt" url="https://blobs.vusercontent.net/blob/customer_schema-0FxPtldtPqdrWJntRDTrFdDZSncy1J.txt"
... This file was left out for brevity. Assume it is correct and does not need any modifications. ...
